Workbook

Sheet Титул
B2: ОТЧЁТ ПО НЕЗАВИСИМОЙ ПРОВЕРКЕ
B4: Контур автоматизации автопарка бензовозов и распределения топлива
B5: BEMOL — сеть АЗС и автопарк бензовозов
B8: СГЕНЕРИРОВАННЫЙ НАБОР ДЛЯ ПРОВЕРКИ МЕТОДИКИ
B10: Предмет проверки | C10: Расчёт заработной платы водителей, планирование и исполнение поставок топлива
B11: Проверяемый период | C11: 2025-09-01 — 2026-09-30
B12: Основание | C12: ТЗ заказчика от 18.09.2026 (два документа): распределение топлива и расходы автопарка
B13: Методика | C13: Методика внутреннего аудита информационных систем: тестирование дизайна и операционной эффективности контролей, тесты по существу на полной популяции (формат отчёта Big-4)
B14: Исполнитель | C14: Группа сопровождения контура «Автопарк»
B15: Дата отчёта | C15: 2026-09-19
B16: Объём популяции | C16: 3534 рейсов, 10576 позиций груза, 77 резервуаров, 14 бензовозов, 22 водителей
B17: Выполнено проверок | C17: 56616 объектов по 13 процедурам
B19: ЗАКЛЮЧЕНИЕ
B20: Контрольная среда неэффективна
B21: Выявлены отклонения высокой значимости: числа, которые контур выдаёт бухгалтерии и руководству, не могут использоваться без ручной перепроверки до устранения находок.
A24: Ограничения проверки
A25: 1. Аудит проверяет внутреннюю непротиворечивость системы и соответствие её собственным правилам. Он не подтверждает достоверность исходных данных: что бензовоз физически проехал маршрут, а в резервуар фактически поступили литры.
A26: 2. Фактический пробег и расход топлива принимаются в том виде, в каком их передаёт GPS-прослойка; независимая сверка с показаниями провайдера в объём работы не входила.
A27: 3. Остатки в резервуарах приняты по данным контура. Сверка с Petrol Expert и инвентаризацией не проводилась — интеграция не подключена.
A28: 4. Заключение относится к периоду и набору данных, указанным на титульном листе, и не распространяется на последующие изменения конфигурации.

Sheet Резюме
A2: Резюме для руководства
A3: Счётчики ниже — формулы по листам «Находки» и «Контроли»: правка реестра меняет резюме сама.
A5: НАХОДОК: ВЫСОКОЙ | D5: НАХОДОК: СРЕДНЕЙ | G5: НАХОДОК: НИЗКОЙ | J5: КОНТРОЛЕЙ ЭФФЕКТИВНЫ
A6: =COUNTIF(Находки!$B:$B,"Высокий") | D6: =COUNTIF(Находки!$B:$B,"Средний") | G6: =COUNTIF(Находки!$B:$B,"Низкий") | J6: =COUNTIF(Контроли!$H:$H,"Эффективен")
A7: требуют устранения до эксплуатации | D7: устранить в согласованный срок | G7: принять к сведению | J7: из 13 контролей контура
A9: ПРОВЕРЕНО ОБЪЕКТОВ | D9: ВЫЯВЛЕНО ОТКЛОНЕНИЙ | G9: ДОЛЯ ОТКЛОНЕНИЙ | J9: ДЕНЕЖНАЯ ОЦЕНКА
A10: 56616 | D10: 616 | G10: 0.0109 | J10: 1219811.1
A11: полная популяция, не выборка | D11: каждое расшифровано на листе «Отклонения» | G11: отклонений к проверенным объектам | J11: лей: лишний пробег, перерасход, потери
B14: Значимость | C14: Находок | E14: Оценка | F14: Контролей
B15: Высокий | C15: =COUNTIF(Находки!$B:$B,"Высокий") | E15: Эффективен | F15: =COUNTIF(Контроли!$H:$H,"Эффективен")
B16: Средний | C16: =COUNTIF(Находки!$B:$B,"Средний") | E16: Требует улучшения | F16: =COUNTIF(Контроли!$H:$H,"Требует улучшения")
B17: Низкий | C17: =COUNTIF(Находки!$B:$B,"Низкий") | E17: Неэффективен | F17: =COUNTIF(Контроли!$H:$H,"Неэффективен")
E18: Не тестировался | F18: =COUNTIF(Контроли!$H:$H,"Не тестировался")
A37: Как читать заключение
A38: • «Контрольная среда неэффективна» — Выявлены отклонения высокой значимости: числа, которые контур выдаёт бухгалтерии и руководству, не могут использоваться без ручной перепроверки до устранения находок.
A39: • Значимость находки не назначается экспертно: она выводится из доли отклонений и денежной оценки по шкале на листе «Методика».
A40: • Контроль с дефектом дизайна не получает оценку выше «требует улучшения», даже если отклонений в периоде не найдено: контроль, который легко обойти, не доказан отсутствием попыток обхода.
A41: • Оценка «не тестировался» означает, что в данных нет реквизита для проверки. Это не «всё хорошо» — это отсутствие доказательства.
A43: Предмет проверки
A44: 1. Расчёт заработной платы водителей бензовозов по нормативному пробегу (ТЗ «Автоматизация расчёта расходов автопарка» от 18.09.2026).
A45: 2. Планирование потребности АЗС в топливе, формирование и исполнение рейсов (ТЗ «Автоматизация распределения топлива» от 18.09.2026).
A46: 3. Контроль фактического пробега и расхода дизельного топлива бензовозами.
A47: 4. Настройки контура, действующие по периодам: ставка за километр, лимиты резервуаров, состав отсеков и групп АЗС.

Sheet Панель BI
A2: BI-панель контура
A3: Измените значение в жёлтой ячейке — показатели и диаграммы пересчитаются в Excel без выгрузки заново.
B6: Месяц | C6: Все | E6: Регион | F6: Все | H6: Продукт | I6: Все | K6: Тип рейса | L6: Все
B9: Поставки — срез по месяцу, региону и продукту
B10: ПРИНЯТО НА АЗС, Л | E10: ПОЗИЦИЙ ГРУЗА | H10: ПОТЕРИ ПРИ ПРИЁМКЕ, Л | K10: ОЦЕНКА ПОТЕРЬ, ЛЕЙ
B11: =SUMPRODUCT(Куб!$H$2:$H$274,Куб!$D$2:$D$274) | E11: =SUMPRODUCT(Куб!$H$2:$H$274,Куб!$E$2:$E$274) | H11: =SUMPRODUCT(Куб!$H$2:$H$274,Куб!$F$2:$F$274) | K11: =SUMPRODUCT(Куб!$H$2:$H$274,Куб!$G$2:$G$274)
B12: по выбранному срезу | E12: отсеков слито | H12: загружено минус принято | K12: по цене продукта
B14: Рейсы и оплата — срез по месяцу и типу рейса
B15: РЕЙСОВ | E15: НОРМАТИВНЫЙ ПРОБЕГ, КМ | H15: ЛИШНИЙ ПРОБЕГ, КМ | K15: НАЧИСЛЕНО, ЛЕЙ
B16: =SUMPRODUCT(КубРейсы!$J$2:$J$27,КубРейсы!$C$2:$C$27) | E16: =SUMPRODUCT(КубРейсы!$J$2:$J$27,КубРейсы!$D$2:$D$27) | H16: =SUMPRODUCT(КубРейсы!$J$2:$J$27,КубРейсы!$F$2:$F$27) | K16: =SUMPRODUCT(КубРейсы!$J$2:$J$27,КубРейсы!$G$2:$G$27)
B17: без черновиков | E17: основание для оплаты | H17: факт сверх норматива | K17: зарплата водителей по срезу
B19: Данные диаграмм — пересчитываются вместе со срезом
B20: Продукт | C20: Принято, л
B21: A92 | C21: =SUMPRODUCT((Куб!$C$2:$C$274=$B21)*Куб!$H$2:$H$274*Куб!$D$2:$D$274)
B22: A95 | C22: =SUMPRODUCT((Куб!$C$2:$C$274=$B22)*Куб!$H$2:$H$274*Куб!$D$2:$D$274)
B23: DIESEL | C23: =SUMPRODUCT((Куб!$C$2:$C$274=$B23)*Куб!$H$2:$H$274*Куб!$D$2:$D$274)
B24: GPL | C24: =SUMPRODUCT((Куб!$C$2:$C$274=$B24)*Куб!$H$2:$H$274*Куб!$D$2:$D$274)
B26: Месяц | C26: Принято, л | D26: Начислено, лей
B27: сентябрь 2025 | C27: =SUMPRODUCT((Куб!$A$2:$A$274="2025-09")*Куб!$I$2:$I$274*Куб!$D$2:$D$274) | D27: =SUMPRODUCT((КубРейсы!$A$2:$A$27="2025-09")*КубРейсы!$K$2:$K$27*КубРейсы!$G$2:$G$27)
B28: октябрь 2025 | C28: =SUMPRODUCT((Куб!$A$2:$A$274="2025-10")*Куб!$I$2:$I$274*Куб!$D$2:$D$274) | D28: =SUMPRODUCT((КубРейсы!$A$2:$A$27="2025-10")*КубРейсы!$K$2:$K$27*КубРейсы!$G$2:$G$27)
B29: ноябрь 2025 | C29: =SUMPRODUCT((Куб!$A$2:$A$274="2025-11")*Куб!$I$2:$I$274*Куб!$D$2:$D$274) | D29: =SUMPRODUCT((КубРейсы!$A$2:$A$27="2025-11")*КубРейсы!$K$2:$K$27*КубРейсы!$G$2:$G$27)
B30: декабрь 2025 | C30: =SUMPRODUCT((Куб!$A$2:$A$274="2025-12")*Куб!$I$2:$I$274*Куб!$D$2:$D$274) | D30: =SUMPRODUCT((КубРейсы!$A$2:$A$27="2025-12")*КубРейсы!$K$2:$K$27*КубРейсы!$G$2:$G$27)
B31: январь 2026 | C31: =SUMPRODUCT((Куб!$A$2:$A$274="2026-01")*Куб!$I$2:$I$274*Куб!$D$2:$D$274) | D31: =SUMPRODUCT((КубРейсы!$A$2:$A$27="2026-01")*КубРейсы!$K$2:$K$27*КубРейсы!$G$2:$G$27)
B32: февраль 2026 | C32: =SUMPRODUCT((Куб!$A$2:$A$274="2026-02")*Куб!$I$2:$I$274*Куб!$D$2:$D$274) | D32: =SUMPRODUCT((КубРейсы!$A$2:$A$27="2026-02")*КубРейсы!$K$2:$K$27*КубРейсы!$G$2:$G$27)
B33: март 2026 | C33: =SUMPRODUCT((Куб!$A$2:$A$274="2026-03")*Куб!$I$2:$I$274*Куб!$D$2:$D$274) | D33: =SUMPRODUCT((КубРейсы!$A$2:$A$27="2026-03")*КубРейсы!$K$2:$K$27*КубРейсы!$G$2:$G$27)
B34: апрель 2026 | C34: =SUMPRODUCT((Куб!$A$2:$A$274="2026-04")*Куб!$I$2:$I$274*Куб!$D$2:$D$274) | D34: =SUMPRODUCT((КубРейсы!$A$2:$A$27="2026-04")*КубРейсы!$K$2:$K$27*КубРейсы!$G$2:$G$27)
B35: май 2026 | C35: =SUMPRODUCT((Куб!$A$2:$A$274="2026-05")*Куб!$I$2:$I$274*Куб!$D$2:$D$274) | D35: =SUMPRODUCT((КубРейсы!$A$2:$A$27="2026-05")*КубРейсы!$K$2:$K$27*КубРейсы!$G$2:$G$27)
B36: июнь 2026 | C36: =SUMPRODUCT((Куб!$A$2:$A$274="2026-06")*Куб!$I$2:$I$274*Куб!$D$2:$D$274) | D36: =SUMPRODUCT((КубРейсы!$A$2:$A$27="2026-06")*КубРейсы!$K$2:$K$27*КубРейсы!$G$2:$G$27)
B37: июль 2026 | C37: =SUMPRODUCT((Куб!$A$2:$A$274="2026-07")*Куб!$I$2:$I$274*Куб!$D$2:$D$274) | D37: =SUMPRODUCT((КубРейсы!$A$2:$A$27="2026-07")*КубРейсы!$K$2:$K$27*КубРейсы!$G$2:$G$27)
B38: август 2026 | C38: =SUMPRODUCT((Куб!$A$2:$A$274="2026-08")*Куб!$I$2:$I$274*Куб!$D$2:$D$274) | D38: =SUMPRODUCT((КубРейсы!$A$2:$A$27="2026-08")*КубРейсы!$K$2:$K$27*КубРейсы!$G$2:$G$27)
B39: сентябрь 2026 | C39: =SUMPRODUCT((Куб!$A$2:$A$274="2026-09")*Куб!$I$2:$I$274*Куб!$D$2:$D$274) | D39: =SUMPRODUCT((КубРейсы!$A$2:$A$27="2026-09")*КубРейсы!$K$2:$K$27*КубРейсы!$G$2:$G$27)
B41: Процедура | C41: Отклонений | D41: Название
B42: T-01 | C42: 18 | D42: Пересчёт заработной платы водителей
B43: T-02 | C43: 0 | D43: Целостность периодов действия ставки
B44: T-03 | C44: 10 | D44: Слив отсеками целиком
B45: T-04 | C45: 5 | D45: Контроль переполнения резервуара
B46: T-05 | C46: 197 | D46: Сверка отгрузки и приёмки
B47: T-06 | C47: 151 | D47: Необоснованный пробег
B48: T-07 | C48: 96 | D48: Перерасход топлива бензовозом
B49: T-08 | C49: 19 | D49: Полнота учёта рейса
B50: T-09 | C50: 35 | D50: Хронология исполнения рейса
B51: T-10 | C51: 74 | D51: Разделение полномочий
B52: T-11 | C52: 3 | D52: Дублирование документов
B53: T-12 | C53: 2 | D53: Непротиворечивость справочников
B54: T-13 | C54: 6 | D54: Покрытие страхового запаса
A57: Что считает панель
A58: • Показатели блока «Поставки» подчиняются трём срезам: месяц, регион, продукт. Блок «Рейсы и оплата» — двум: месяц и тип рейса; регион к рейсу не относится, один рейс обслуживает несколько АЗС.
A59: • Диаграммы динамики намеренно не подчиняются срезу по месяцу: иначе на графике осталась бы одна точка. Срезы по региону и продукту они соблюдают.
A60: • Источник всех чисел — листы «Куб» и «КубРейсы»; колонки «В срезе» на них — формулы, читающие жёлтые ячейки этой панели.

Sheet Контроли
A2: Матрица контролей
A3: Дизайн — предотвращает ли правило ошибку в принципе. Эффективность — сработало ли оно на данных периода.
A5: Код | B5: Область | C5: Контроль | D5: Цель контроля | E5: Тип | F5: Дизайн | G5: Эффективность | H5: Итоговая оценка | I5: Покрытие | J5: Проверено | K5: Отклонений | L5: Оценка, лей
A6: FLT-C-01 | B6: Расчёты с персоналом | C6: Автоматический расчёт зарплаты по нормативу | D6: Зарплата водителя рассчитывается системой по нормативному пробегу и не вводится вручную. | E6: Автоматический | F6: Эффективен | G6: Требует улучшения | H6: Требует улучшения | I6: 100 % популяции | J6: 3515 | K6: 18 | L6: 2622.71
A7: FLT-C-02 | B7: Расчёты с персоналом | C7: Ставка применяется по дате рейса | D7: Изменение ставки не переписывает начисления закрытых периодов. | E7: Автоматический | F7: Эффективен | G7: Требует улучшения | H7: Требует улучшения | I7: 100 % популяции | J7: 3516 | K7: 18 | L7: 2622.71
A8: FLT-C-03 | B8: Операции: отгрузка и приёмка | C8: Слив отсеками целиком | D8: Плановый объём позиции равен паспортному объёму отсека. | E8: Автоматический | F8: Эффективен | G8: Требует улучшения | H8: Требует улучшения | I8: 100 % популяции | J8: 10576 | K8: 10 | L8: 0
A9: FLT-C-04 | B9: Операции: отгрузка и приёмка | C9: Запрет переполнения резервуара | D9: Приёмка не превышает свободную ёмкость резервуара. | E9: Автоматический | F9: Эффективен | G9: Требует улучшения | H9: Требует улучшения | I9: 100 % популяции | J9: 10576 | K9: 5 | L9: 0
A10: FLT-C-05 | B10: Операции: отгрузка и приёмка | C10: Сверка отгруженного и принятого | D10: Расхождение выявляется и фиксируется по каждой поставке. | E10: Автоматический | F10: Эффективен | G10: Требует улучшения | H10: Требует улучшения | I10: 100 % популяции | J10: 10576 | K10: 197 | L10: 1132934.4
A11: FLT-C-06 | B11: Контроль затрат | C11: Контроль необоснованного пробега | D11: Превышение факта над нормативом выявляется и оценивается в деньгах. | E11: Автоматический | F11: Эффективен | G11: Требует улучшения | H11: Требует улучшения | I11: 100 % популяции | J11: 3534 | K11: 151 | L11: 30259.6
A12: FLT-C-07 | B12: Контроль затрат | C12: Контроль расхода топлива бензовозом | D12: Перерасход против нормы автомобиля выявляется. | E12: Автоматический | F12: Эффективен | G12: Требует улучшения | H12: Требует улучшения | I12: 100 % популяции | J12: 3534 | K12: 96 | L12: 53994.44
A13: FLT-C-08 | B13: Полнота и достоверность учёта | C13: Полнота реквизитов рейса | D13: Утверждённый рейс содержит груз, норматив и начисление. | E13: Автоматический | F13: Эффективен | G13: Требует улучшения | H13: Требует улучшения | I13: 100 % популяции | J13: 3534 | K13: 19 | L13: 0
A14: FLT-C-09 | B14: Полнота и достоверность учёта | C14: Цепочка статусов исполнения | D14: Документ нельзя оформить задним числом, пропустив стадии. | E14: Автоматический | F14: Требует улучшения | G14: Требует улучшения | H14: Требует улучшения | I14: 100 % популяции | J14: 3534 | K14: 35 | L14: 0
A15: FLT-C-10 | B15: Доступ и полномочия | C15: Разделение полномочий «создал / утвердил» | D15: Одно лицо не создаёт и не утверждает один и тот же рейс. | E15: Ручной | F15: Требует улучшения | G15: Требует улучшения | H15: Требует улучшения | I15: Выборка | J15: 3534 | K15: 74 | L15: 0
A16: FLT-C-11 | B16: Полнота и достоверность учёта | C16: Защита от двойного учёта | D16: Рейс и путевой лист не учитываются дважды. | E16: Автоматический | F16: Эффективен | G16: Требует улучшения | H16: Требует улучшения | I16: 100 % популяции | J16: 3534 | K16: 3 | L16: 0
A17: FLT-C-12 | B17: Справочные данные | C17: Непротиворечивость справочников | D17: Паспортные величины не противоречат друг другу. | E17: Автоматический | F17: Эффективен | G17: Требует улучшения | H17: Требует улучшения | I17: 100 % популяции | J17: 91 | K17: 2 | L17: 0
A18: FLT-C-13 | B18: Непрерывность операций | C18: Покрытие страхового запаса планом завоза | D18: АЗС не останавливает продажу из-за отсутствия топлива. | E18: Автоматический | F18: Эффективен | G18: Неэффективен | H18: Неэффективен | I18: 100 % популяции | J18: 77 | K18: 6 | L18: 0
A20: Обоснование оценки дизайна
A21: Почему контроль признан эффективным или требующим улучшения — и какой процедурой это проверено.
A23: Код | B23: Как контроль реализован в системе | C23: Процедуры проверки
A24: FLT-C-01 | B24: Начисление формируется представлением V_FLT_TRIP_PAY; поля для ручного ввода суммы в интерфейсе нет. | C24: T-01
A25: FLT-C-02 | B25: Ставки хранятся периодами (FLT_RATE_PERIODS), резолвер выбирает период по TRIP_DATE, а не по SYSDATE. | C25: T-02, T-01
A26: FLT-C-03 | B26: Подбор отсеков — точное перечисление подмножеств (supply_rules.pick_sections), частичный объём сформировать нельзя. | C26: T-03
A27: FLT-C-04 | B27: Валидация на сервере (supply_rules.validate_loads); проверка выполняется до сохранения факта. | C27: T-04
A28: FLT-C-05 | B28: Карточка исполнения показывает три величины (загружено / по документам / принято) и подсвечивает разницу. | C28: T-05
A29: FLT-C-06 | B29: Порог отклонения — настройка заказчика (KM_DEVIATION_LIMIT), факт приходит из GPS-прослойки. | C29: T-06
A30: FLT-C-07 | B30: Норма хранится в карточке автомобиля (NORM_L_PER_100KM), расчёт нормы рейса автоматический. | C30: T-07
A31: FLT-C-08 | B31: Утверждение недоступно для рейса без позиций; нормативный пробег считается при сохранении маршрута. | C31: T-08
A32: FLT-C-09 | B32: Порядок задан справочником REF_TRIP_STATUS.SORT_NO, но запрет обратного перехода реализован в контроллере, а не ограничением БД — прямая правка таблицы его обойдёт. | C32: T-09
A33: FLT-C-10 | B33: Роли в системе разделены, но техническая блокировка самоутверждения не включена: контроль держится на распределении учётных записей. | C33: T-10
A34: FLT-C-11 | B34: Один бензовоз используется в плане один раз; номер путевого листа уникален. | C34: T-11
... A36: FLT-C-13 | B36: Планирование сортирует потребности по дням до страхового запаса; сводка руководителя показывает риск. | C36: T-13

Sheet Находки
A2: Реестр находок
A3: Три последние колонки — для ответа руководства; их заполняет заказчик, остальное считает проверка.
A5: № | B5: Значимость | C5: Контроль | D5: Тест | E5: Наблюдение | F5: Риск | G5: Рекомендация | H5: Отклонений | I5: Проверено | J5: Доля | K5: Оценка, лей | L5: Вероятн. 1–5 | M5: Влияние 1–5 | N5: Ответственный | O5: Срок | P5: Статус устранения
A6: F-01 | B6: Высокий | C6: FLT-C-05 | D6: T-05 | E6: При проверке 10576 объектов (100 % позиций с зафиксированными отгрузкой и приёмкой) выявлено 197 отклонений (1.86 %). Денежная оценка: 1 132 934.40 лея. | F6: Систематическая недостача при приёмке — признак потерь продукта или недолива на нефтебазе. | G6: Ввести разбор каждой недостачи выше допуска с обязательным комментарием и сверкой с нефтебазой. | H6: 197 | I6: 10576 | J6: 0.0186 | K6: 1132934.4 | L6: 3 | M6: 5
A7: F-02 | B7: Высокий | C7: FLT-C-07 | D7: T-07 | E7: При проверке 3534 объектов (100 % рейсов с зафиксированной заправкой) выявлено 96 отклонений (2.72 %). Денежная оценка: 53 994.44 лея. | F7: Перерасход топлива бензовозом — прямой убыток и возможный слив на сторону. | G7: Сверять заправки бензовозов с топливными картами и разбирать рейсы с отклонением выше порога. | H7: 96 | I7: 3534 | J7: 0.0272 | K7: 53994.44 | L7: 3 | M7: 5
A8: F-03 | B8: Высокий | C8: FLT-C-13 | D8: T-13 | E8: При проверке 77 объектов (100 % резервуаров сети) выявлено 6 отклонений (7.79 %). | F8: Остановка продажи на АЗС из-за отсутствия топлива — потерянная выручка и репутационный ущерб. | G8: Включить резервуары ниже страхового запаса в план завоза принудительно, с уведомлением логисту. | H8: 6 | I8: 77 | J8: 0.0779 | K8: 0 | L8: 4 | M8: 2
A9: F-04 | B9: Средний | C9: FLT-C-06 | D9: T-06 | E9: При проверке 3534 объектов (100 % рейсов с зафиксированным фактическим пробегом) выявлено 151 отклонений (4.27 %). Денежная оценка: 30 259.60 лея. | F9: Лишние километры оплачиваются водителю и не создают поставки. | G9: Требовать обоснование при утверждении рейса с отклонением выше порога. | H9: 151 | I9: 3534 | J9: 0.0427 | K9: 30259.6 | L9: 3 | M9: 4
A10: F-05 | B10: Средний | C10: FLT-C-10 | D10: T-10 | E10: При проверке 3534 объектов (100 % утверждённых рейсов с заполненными автором и утвердившим) выявлено 74 отклонений (2.09 %). | F10: Самоутверждение рейса снимает единственный контроль над основанием для начисления зарплаты. | G10: Включить техническую блокировку: утвердить рейс может только учётная запись, отличная от создавшей. | H10: 74 | I10: 3534 | J10: 0.0209 | K10: 0 | L10: 3 | M10: 2
A11: F-06 | B11: Средний | C11: FLT-C-12 | D11: T-12 | E11: При проверке 91 объектов (100 % резервуаров и бензовозов) выявлено 2 отклонений (2.20 %). | F11: Ошибка в справочнике тиражируется во все расчёты периода и обнаруживается только при инвентаризации. | G11: Проверять неравенства при сохранении карточки и ежемесячно прогонять контроль справочников. | H11: 2 | I11: 91 | J11: 0.022 | K11: 0 | L11: 3 | M11: 1
A12: F-07 | B12: Низкий | C12: FLT-C-01 | D12: T-01 | E12: При проверке 3515 объектов (100 % рейсов периода со статусом не «черновик») выявлено 18 отклонений (0.51 %). Денежная оценка: 2 622.71 лея. | F12: Начисление, не соответствующее нормативу, попадает в расчётную ведомость и в себестоимость литра. | G12: Заблокировать сохранение рейса, у которого начисление отличается от расчётного, и вывести расхождение в журнал для разбора. | H12: 18 | I12: 3515 | J12: 0.0051 | K12: 2622.71 | L12: 2 | M12: 3
A13: F-08 | B13: Низкий | C13: FLT-C-03 | D13: T-03 | E13: При проверке 10576 объектов (100 % позиций рейсов с назначенным отсеком) выявлено 10 отклонений (0.09 %). | F13: Частичный слив нечем измерить: остаток в отсеке становится неучтённым топливом. | G13: Оставить подбор отсеков только автоматическим, ручное изменение объёма позиции запретить. | H13: 10 | I13: 10576 | J13: 0.0009 | K13: 0 | L13: 1 | M13: 2
A14: F-09 | B14: Низкий | C14: FLT-C-04 | D14: T-04 | E14: При проверке 10576 объектов (100 % позиций с зафиксированным объёмом) выявлено 5 отклонений (0.05 %). | F14: Перелив резервуара — пролив продукта, экологический инцидент и прямые потери. | G14: Держать проверку на сервере (не в форме) и логировать каждую попытку превышения. | H14: 5 | I14: 10576 | J14: 0.0005 | K14: 0 | L14: 1 | M14: 1
A15: F-10 | B15: Низкий | C15: FLT-C-08 | D15: T-08 | E15: При проверке 3534 объектов (100 % рейсов периода со статусом не «черновик») выявлено 19 отклонений (0.54 %). | F15: Неполный рейс не может служить основанием для начисления и списания, но участвует в отчётности. | G15: Запретить утверждение рейса без позиций груза и рассчитанного норматива. | H15: 19 | I15: 3534 | J15: 0.0054 | K15: 0 | L15: 2 | M15: 2
A16: F-11 | B16: Низкий | C16: FLT-C-09 | D16: T-09 | E16: При проверке 3534 объектов (100 % рейсов с журналом статусов) выявлено 35 отклонений (0.99 %). | F16: Оформление задним числом скрывает простои и фактические сроки доставки. | G16: Перенести проверку порядка статусов в ограничение базы данных (триггер), чтобы её нельзя было обойти прямой правкой таблицы. | H16: 35 | I16: 3534 | J16: 0.0099 | K16: 0 | L16: 2 | M16: 2
A17: F-12 | B17: Низкий | C17: FLT-C-11 | D17: T-11 | E17: При проверке 3534 объектов (100 % рейсов периода со статусом не «черновик») выявлено 3 отклонений (0.08 %). | F17: Двойной учёт рейса удваивает и зарплату, и списание топлива. | G17: Добавить уникальный ключ на номер путевого листа и предупреждение при повторной постановке бензовоза. | H17: 3 | I17: 3534 | J17: 0.0008 | K17: 0 | L17: 1 | M17: 1
A19: Заполняет заказчик
A20: • Жёлтые ячейки колонок «Ответственный», «Срок» и «Статус устранения» — единственные, которые вносит заказчик. Например: «Морару И., руководитель транспортного отдела» / «31.10.2026» / «Принято, в работе».
A21: • Остальные колонки рассчитаны проверкой; их правка разрывает связь с листами «Тесты» и «Отклонения» и делает отчёт непроверяемым.
A22: • Значимость: «Высокий» — доля отклонений ≥ 5 % либо денежная оценка ≥ 50 000 лей; «Средний» — ≥ 1 % либо ≥ 5 000 лей; «Низкий» — всё остальное.

Sheet Карта рисков
A2: Карта рисков: вероятность × влияние
A3: Обе координаты выведены из результата тестирования — из доли отклонений и денежной оценки, а не назначены.
B6: ВЛИЯНИЕ | C6: 5 | F6: F-01, F-02
C7: 4 | F7: F-04
C8: 3 | E8: F-07
C9: 2 | D9: F-08 | E9: F-10, F-11 | F9: F-05 | G9: F-03
C10: 1 | D10: F-09, F-12 | F10: F-06
D11: 1 | E11: 2 | F11: 3 | G11: 4 | H11: 5
D12: ВЕРОЯТНОСТЬ
A14: Находки на карте
A16: № | B16: Находка | C16: Значимость | D16: Вероятность | E16: Влияние | F16: Ранг
A17: F-01 | B17: Сверка отгрузки и приёмки | C17: Высокий | D17: 3 | E17: 5 | F17: 15
A18: F-02 | B18: Перерасход топлива бензовозом | C18: Высокий | D18: 3 | E18: 5 | F18: 15
A19: F-04 | B19: Необоснованный пробег | C19: Средний | D19: 3 | E19: 4 | F19: 12
A20: F-03 | B20: Покрытие страхового запаса | C20: Высокий | D20: 4 | E20: 2 | F20: 8
A21: F-05 | B21: Разделение полномочий | C21: Средний | D21: 3 | E21: 2 | F21: 6
A22: F-07 | B22: Пересчёт заработной платы водителей | C22: Низкий | D22: 2 | E22: 3 | F22: 6
A23: F-10 | B23: Полнота учёта рейса | C23: Низкий | D23: 2 | E23: 2 | F23: 4
A24: F-11 | B24: Хронология исполнения рейса | C24: Низкий | D24: 2 | E24: 2 | F24: 4
A25: F-06 | B25: Непротиворечивость справочников | C25: Средний | D25: 3 | E25: 1 | F25: 3
A26: F-08 | B26: Слив отсеками целиком | C26: Низкий | D26: 1 | E26: 2 | F26: 2
A27: F-09 | B27: Контроль переполнения резервуара | C27: Низкий | D27: 1 | E27: 1 | F27: 1
A28: F-12 | B28: Дублирование документов | C28: Низкий | D28: 1 | E28: 1 | F28: 1
A30: Шкала
A31: • Вероятность 5 — отклонения более чем в 10 % проверенных объектов; 4 — свыше 5 %; 3 — свыше 1 %; 2 — свыше 0,1 %; 1 — единичные.
A32: • Влияние 5 — денежная оценка от 50 000 лей; 4 — от 5 000; 3 — от 500; 2 — оценка ниже 500 лей либо более пяти случаев; 1 — единичный случай без денежной оценки.
A33: • Ранг = вероятность × влияние. Красная зона — устранять до перевода контура в промышленную эксплуатацию.

Sheet Тесты
A2: Выполненные процедуры
A3: Пересчёт выполнен отдельной реализацией формул, не использующей проверяемый код: совпадение результата не может быть следствием общей ошибки.
A5: Код | B5: Процедура | C5: Что должно выполняться | D5: Как проверено | E5: Охват | F5: Проверено | G5: Отклонений | H5: Доля | I5: Оценка, лей | J5: Результат
A6: T-01 | B6: Пересчёт заработной платы водителей | C6: Начисление соответствует нормативному пробегу и ставке, действовавшей на дату рейса. | D6: Пересчёт: норм. км × ставка(дата рейса) + доплата за внутренний рейс. Сравнение с начислением в системе, допуск 0,01 лея. | E6: 100 % рейсов периода со статусом не «черновик» | F6: 3515 | G6: 18 | H6: 0.0051 | I6: 2622.71 | J6: Отклонения
A7: T-02 | B7: Целостность периодов действия ставки | C7: На любую дату действует ровно одна ставка; изменение ставки не меняет уже начисленное за прошлый период. | D7: Сортировка периодов по дате начала, проверка смежности: предыдущий закрыт строго до начала следующего. | E7: 100 % периодов действия ставки | F7: 1 | G7: 0 | H7: 0 | I7: 0 | J7: Без отклонений
A8: T-03 | B8: Слив отсеками целиком | C8: Отсек бензовоза сливается на АЗС полностью: частичный слив ТЗ запрещает (нет поверенного средства измерения остатка в отсеке). | D8: Сверка планового объёма каждой позиции с паспортным объёмом назначенного отсека, допуск 0,5 л. | E8: 100 % позиций рейсов с назначенным отсеком | F8: 10576 | G8: 10 | H8: 0.0009 | I8: 0 | J8: Отклонения
A9: T-04 | B9: Контроль переполнения резервуара | C9: Приёмка не может превысить допустимый налив резервуара, а для ещё не выполненной поставки — свободную ёмкость на сегодня. | D9: Для запланированных поставок: приёмка против (допустимый налив − остаток). Для исполненных: приёмка против допустимого налива (состояние резервуара на дату слива контур не хранит). Допуск 0,5 л. | E9: 100 % позиций с зафиксированным объёмом | F9: 10576 | G9: 5 | H9: 0.0005 | I9: 0 | J9: Отклонения
A10: T-05 | B10: Сверка отгрузки и приёмки | C10: Расхождение между налитым на нефтебазе и принятым на АЗС не превышает технологического допуска. | D10: Разница «загружено − принято» по каждой позиции против допуска 50 л; денежная оценка по цене ДТ. | E10: 100 % позиций с зафиксированными отгрузкой и приёмкой | F10: 10576 | G10: 197 | H10: 0.0186 | I10: 1132934.4 | J10: Отклонения
A11: T-06 | B11: Необоснованный пробег | C11: Фактический пробег не превышает нормативный более чем на 5 %. | D11: Расчёт отклонения по каждому рейсу с фактом GPS; денежная оценка лишних километров по действующей ставке. | E11: 100 % рейсов с зафиксированным фактическим пробегом | F11: 3534 | G11: 151 | H11: 0.0427 | I11: 30259.6 | J11: Отклонения
A12: T-07 | B12: Перерасход топлива бензовозом | C12: Фактический расход ДТ не превышает норму автомобиля более чем на 5 %. | D12: Норма рейса = норм. км × норма л/100 км автомобиля; сравнение с фактической заправкой, денежная оценка по цене ДТ. | E12: 100 % рейсов с зафиксированной заправкой | F12: 3534 | G12: 96 | H12: 0.0272 | I12: 53994.44 | J12: Отклонения
A13: T-08 | B13: Полнота учёта рейса | C13: Утверждённый рейс содержит груз, нормативный пробег и начисление — иначе он не может быть основанием ни для зарплаты, ни для списания топлива. | D13: Проверка наличия связанных записей у каждого рейса не в статусе «черновик». | E13: 100 % рейсов периода со статусом не «черновик» | F13: 3534 | G13: 19 | H13: 0.0054 | I13: 0 | J13: Отклонения
A14: T-09 | B14: Хронология исполнения рейса | C14: Статусы меняются строго по цепочке: заявка → загрузка → в пути → доставлено → утверждено. Пропуск стадии означает, что документ оформлен задним числом. | D14: Проверка последовательности записей журнала статусов каждого рейса против эталонной цепочки. | E14: 100 % рейсов с журналом статусов | F14: 3534 | G14: 35 | H14: 0.0099 | I14: 0 | J14: Отклонения
A15: T-10 | B15: Разделение полномочий | C15: Создание рейса и его утверждение выполняют разные сотрудники: утверждённый рейс — основание для начисления зарплаты. | D15: Сравнение автора и утвердившего по каждому утверждённому рейсу. | E15: 100 % утверждённых рейсов с заполненными автором и утвердившим | F15: 3534 | G15: 74 | H15: 0.0209 | I15: 0 | J15: Отклонения
A16: T-11 | B16: Дублирование документов | C16: Один и тот же рейс не может быть учтён дважды — ни через второй путевой лист, ни через полностью повторённый документ. | D16: Поиск повторов по номеру путевого листа и по полному совпадению реквизитов (бензовоз, дата, водитель, нормативный пробег) по всей популяции рейсов. Два разных рейса одной машины за день отклонением не считаются. | E16: 100 % рейсов периода со статусом не «черновик» | F16: 3534 | G16: 3 | H16: 0.0008 | I16: 0 | J16: Отклонения
A17: T-12 | B17: Непротиворечивость справочников | C17: Паспортные величины резервуаров и бензовозов не противоречат друг другу: на них опираются все последующие расчёты. | D17: Проверка неравенств: налив ≤ ёмкость, страховой запас ≤ налив, остаток ≤ ёмкость, сумма отсеков = ёмкость цистерны. | E17: 100 % резервуаров и бензовозов | F17: 91 | G17: 2 | H17: 0.022 | I17: 0 | J17: Отклонения
A18: T-13 | B18: Покрытие страхового запаса | C18: Резервуар с остатком ниже страхового запаса включён в план завоза: иначе АЗС останавливает продажу. | D18: Сопоставление резервуаров ниже страхового запаса с позициями запланированных рейсов. | E18: 100 % резервуаров сети | F18: 77 | G18: 6 | H18: 0.0779 | I18: 0 | J18: Отклонения
A20: Методика
A21: 1. Тестирование полной популяции (data & analytics): каждый документ периода пересчитан независимо, выборочный метод применён только там, где контроль не отражён в данных.
A22: 2. Пересчёт выполнен отдельной реализацией формул (modules/autopark/audit.py), не использующей проверяемый код расчёта, — совпадение результата не может быть следствием общей ошибки.
A23: 3. Оценка контроля даётся по двум измерениям: дизайн (предотвращает ли правило ошибку в принципе) и операционная эффективность (срабатывало ли оно на данных периода).
A24: 4. Контроль с дефектом дизайна не получает оценку выше «требует улучшения», даже если отклонений в периоде не обнаружено.
A25: 5. Значимость находки определяется долей отклонений и денежной оценкой, а не экспертным суждением.

Sheet Отклонения
A2: Расшифровка отклонений
A3: Каждый выявленный случай с реквизитами документа — чтобы находку можно было проверить, а не принять на веру.
A5: T-01 · Пересчёт заработной платы водителей · отклонений: 18 из 3515 проверенных
A6: Рейс | B6: Дата | C6: Водитель | D6: Тип | E6: Норм. км | F6: Ставка | G6: Пересчёт аудитора, лей | H6: В системе, лей | I6: Расхождение, лей
A7: 62 | B7: 2025-09-06 | C7: Rusu Victor | D7: DOMESTIC | E7: 189.3 | F7: 2.75 | G7: 1120.58 | H7: 1267.83 | I7: 147.25
A8: 108 | B8: 2025-09-12 | C8: Sirbu Dumitru | D8: DOMESTIC | E8: 258.7 | F8: 2.75 | G8: 1311.42 | H8: 1495.97 | I8: 184.55
A9: 133 | B9: 2025-09-16 | C9: Rotaru Igor | D9: DOMESTIC | E9: 296.7 | F9: 2.75 | G9: 1415.92 | H9: 1520.98 | I9: 105.06
A10: 397 | B10: 2025-10-15 | C10: Cazacu Petru | D10: DOMESTIC | E10: 210.5 | F10: 2.75 | G10: 1178.88 | H10: 1251.18 | I10: 72.31
A11: 516 | B11: 2025-10-29 | C11: Rotaru Dumitru | D11: DOMESTIC | E11: 291.4 | F11: 2.75 | G11: 1401.35 | H11: 1513.41 | I11: 112.06
A12: 723 | B12: 2025-11-24 | C12: Cazacu Mihai | D12: DOMESTIC | E12: 309 | F12: 2.75 | G12: 1449.75 | H12: 1538.33 | I12: 88.58
A13: 990 | B13: 2025-12-22 | C13: Grosu Petru | D13: IMPORT | E13: 977 | F13: 2.75 | G13: 2686.75 | H13: 2934.15 | I13: 247.4
A14: 1563 | B14: 2026-02-23 | C14: Rusu Petru | D14: DOMESTIC | E14: 293.5 | F14: 2.75 | G14: 1407.12 | H14: 1550.23 | I14: 143.11
A15: 1756 | B15: 2026-03-17 | C15: Grosu Petru | D15: DOMESTIC | E15: 399.7 | F15: 2.75 | G15: 1699.17 | H15: 1993.45 | I15: 294.28
A16: 1895 | B16: 2026-03-31 | C16: Popa Mihai | D16: DOMESTIC | E16: 194.6 | F16: 2.75 | G16: 1135.15 | H16: 1219.5 | I16: 84.35
A17: 2002 | B17: 2026-04-11 | C17: Cebotari Andrei | D17: DOMESTIC | E17: 446.8 | F17: 2.75 | G17: 1828.7 | H17: 1906.43 | I17: 77.73
A18: 2433 | B18: 2026-05-29 | C18: Bejan Mihai | D18: DOMESTIC | E18: 232.7 | F18: 2.75 | G18: 1239.92 | H18: 1279.92 | I18: 40
... A24: 3334 | B24: 2026-09-08 | C24: Chirica Igor | D24: DOMESTIC | E24: 320.9 | F24: 3.5 | G24: 1123.15 | H24: 1306.43 | I24: 183.28
A27: T-03 · Слив отсеками целиком · отклонений: 10 из 10576 проверенных
A28: Рейс | B28: АЗС | C28: Продукт | D28: Отсек | E28: Объём отсека, л | F28: В позиции, л | G28: Расхождение, л
A29: 201 | B29: КОМ-24 | C29: A92 | D29: 3 | E29: 4000 | F29: 3171 | G29: -829
A30: 1150 | B30: КОМ-18 | C30: A95 | D30: 27 | E30: 6000 | F30: 4736 | G30: -1264
A31: 1371 | B31: БЭЛ-14 | C31: A92 | D31: 53 | E31: 3000 | F31: 2350 | G31: -650
A32: 1493 | B32: УНГ-05 | C32: DIESEL | D32: 10 | E32: 6000 | F32: 3814 | G32: -2186
A33: 2402 | B33: УНГ-17 | C33: A92 | D33: 13 | E33: 6000 | F33: 4934 | G33: -1066
A34: 2699 | B34: КАГ-09 | C34: A95 | D34: 17 | E34: 4000 | F34: 2846 | G34: -1154
A35: 3377 | B35: УНГ-05 | C35: A92 | D35: 45 | E35: 4000 | F35: 3165 | G35: -835
A36: 3406 | B36: КИШ-19 | C36: A92 | D36: 20 | E36: 5000 | F36: 2918 | G36: -2082
A37: 3428 | B37: УНГ-05 | C37: DIESEL | D37: 15 | E37: 4000 | F37: 3118 | G37: -882
A38: 3487 | B38: УНГ-17 | C38: DIESEL | D38: 19 | E38: 5000 | F38: 2813 | G38: -2187
A41: T-04 · Контроль переполнения резервуара · отклонений: 5 из 10576 проверенных
A42: Рейс | B42: АЗС | C42: Продукт | D42: База сравнения | E42: Допустимый налив, л | F42: Остаток, л | G42: Предел, л | H42: Принято, л | I42: Превышение, л
A43: 917 | B43: КИШ-01 | C43: A92 | D43: допустимый налив резервуара | E43: 28500 | F43: 20728 | G43: 28500 | H43: 29273 | I43: 773
A44: 1102 | B44: ОРХ-16 | C44: A92 | D44: допустимый налив резервуара | E44: 23750 | F44: 15842 | G44: 23750 | H44: 24471 | I44: 721
A45: 1739 | B45: БЭЛ-02 | C45: DIESEL | D45: допустимый налив резервуара | E45: 38000 | F45: 14226 | G45: 38000 | H45: 39950 | I45: 1950
A46: 1958 | B46: ОРХ-10 | C46: A92 | D46: допустимый налив резервуара | E46: 19000 | F46: 13409 | G46: 19000 | H46: 20545 | I46: 1545
A47: 2820 | B47: КАГ-21 | C47: A95 | D47: допустимый налив резервуара | E47: 19000 | F47: 16835 | G47: 19000 | H47: 20314 | I47: 1314
A50: T-05 · Сверка отгрузки и приёмки · отклонений: 197 из 10576 проверенных
A51: Рейс | B51: АЗС | C51: Продукт | D51: Загружено, л | E51: По документам, л | F51: Принято, л | G51: Потери, л | H51: Оценка, лей
A52: 2 | B52: БЭЛ-02 | C52: A92 | D52: 6000 | E52: 6000 | F52: 5588 | G52: 412 | H52: 9640.8
A53: 3 | B53: КИШ-19 | C53: DIESEL | D53: 5000 | E53: 5000 | F53: 4930 | G53: 70 | H53: 1638
A54: 36 | B54: БЭЛ-20 | C54: DIESEL | D54: 6000 | E54: 6000 | F54: 5895 | G54: 105 | H54: 2457
A55: 36 | B55: КОМ-06 | C55: GPL | D55: 6000 | E55: 6000 | F55: 5589 | G55: 411 | H55: 9617.4
A56: 41 | B56: УНГ-05 | C56: A95 | D56: 6000 | E56: 6000 | F56: 5767 | G56: 233 | H56: 5452.2
A57: 47 | B57: ОРХ-16 | C57: A92 | D57: 5000 | E57: 5000 | F57: 4779 | G57: 221 | H57: 5171.4
A58: 57 | B58: ОРХ-22 | C58: A95 | D58: 4000 | E58: 4000 | F58: 3582 | G58: 418 | H58: 9781.2
A59: 63 | B59: КИШ-19 | C59: A95 | D59: 3000 | E59: 3000 | F59: 2641 | G59: 359 | H59: 8400.6
A60: 93 | B60: КОМ-06 | C60: DIESEL | D60: 6000 | E60: 6000 | F60: 5630 | G60: 370 | H60: 8658
A61: 117 | B61: УНГ-05 | C61: A95 | D61: 4000 | E61: 4000 | F61: 3823 | G61: 177 | H61: 4141.8
A62: 147 | B62: КОМ-06 | C62: DIESEL | D62: 4000 | E62: 4000 | F62: 3900 | G62: 100 | H62: 2340
A63: 204 | B63: УНГ-11 | C63: A95 | D63: 5000 | E63: 5000 | F63: 4693 | G63: 307 | H63: 7183.8
... A248: 3533 | B248: ОРХ-22 | C248: A95 | D248: 5000 | E248: 5000 | F248: 4902 | G248: 98 | H248: 2293.2
A251: T-06 · Необоснованный пробег · отклонений: 151 из 3534 проверенных
A252: Рейс | B252: Дата | C252: Водитель | D252: Норматив, км | E252: Факт, км | F252: Отклонение, % | G252: Оценка, лей
A253: 12 | B253: 2025-09-02 | C253: Cebotari Sergiu | D253: 694.8 | E253: 796.6 | F253: 14.65 | G253: 356.3
A254: 31 | B254: 2025-09-03 | C254: Ursu Ion | D254: 862.4 | E254: 977.2 | F254: 13.31 | G254: 401.8
A255: 41 | B255: 2025-09-04 | C255: Bejan Mihai | D255: 981.9 | E255: 1098.9 | F255: 11.92 | G255: 409.5
A256: 44 | B256: 2025-09-04 | C256: Ursu Ion | D256: 231.3 | E256: 275.9 | F256: 19.28 | G256: 156.1
A257: 90 | B257: 2025-09-10 | C257: Rotaru Dumitru | D257: 359 | E257: 385.1 | F257: 7.27 | G257: 91.35
A258: 106 | B258: 2025-09-12 | C258: Rotaru Dumitru | D258: 471.9 | E258: 549.3 | F258: 16.4 | G258: 270.9
A259: 127 | B259: 2025-09-15 | C259: Bejan Mihai | D259: 409.4 | E259: 463.8 | F259: 13.29 | G259: 190.4
A260: 141 | B260: 2025-09-16 | C260: Stratan Dumitru | D260: 455.8 | E260: 499.9 | F260: 9.68 | G260: 154.35
A261: 157 | B261: 2025-09-18 | C261: Popa Victor | D261: 228.3 | E261: 253.8 | F261: 11.17 | G261: 89.25
A262: 194 | B262: 2025-09-22 | C262: Cebotari Sergiu | D262: 303.3 | E262: 325.5 | F262: 7.32 | G262: 77.7
A263: 198 | B263: 2025-09-23 | C263: Balan Grigore | D263: 323 | E263: 368.9 | F263: 14.21 | G263: 160.65
A264: 218 | B264: 2025-09-25 | C264: Bejan Mihai | D264: 173.6 | E264: 190 | F264: 9.45 | G264: 57.4
... A403: 3486 | B403: 2026-09-25 | C403: Cebotari Sergiu | D403: 240.8 | E403: 276.9 | F403: 14.99 | G403: 126.35
A406: T-07 · Перерасход топлива бензовозом · отклонений: 96 из 3534 проверенных
A407: Рейс | B407: Дата | C407: Автомобиль | D407: Норма, л | E407: Факт, л | F407: Отклонение, % | G407: Оценка, лей
A408: 89 | B408: 2025-09-10 | C408: T859HH | D408: 73.8 | E408: 82.7 | F408: 12.1 | G408: 208.89
A409: 116 | B409: 2025-09-13 | C409: N296BB | D409: 61.6 | E409: 75.4 | F409: 22.42 | G409: 323.1
A410: 137 | B410: 2025-09-16 | C410: T859HH | D410: 114 | E410: 135.8 | F410: 19.1 | G410: 509.68
A411: 171 | B411: 2025-09-19 | C411: P246JJ | D411: 59.3 | E411: 65.5 | F411: 10.46 | G411: 145.2
A412: 337 | B412: 2025-10-09 | C412: C446BH | D412: 57.4 | E412: 73 | F412: 27.19 | G412: 365.16
A413: 344 | B413: 2025-10-09 | C413: A359DA | D413: 109.5 | E413: 128.4 | F413: 17.27 | G413: 442.45
A414: 346 | B414: 2025-10-09 | C414: C832JB | D414: 84.6 | E414: 100.6 | F414: 18.97 | G414: 375.34
A415: 389 | B415: 2025-10-14 | C415: K715EH | D415: 126.6 | E415: 147.6 | F415: 16.57 | G415: 490.96
A416: 407 | B416: 2025-10-16 | C416: K715EH | D416: 107.5 | E416: 127.9 | F416: 18.95 | G416: 476.83
A417: 411 | B417: 2025-10-16 | C417: N558HD | D417: 132.6 | E417: 148.6 | F417: 12.11 | G417: 375.47
A418: 483 | B418: 2025-10-25 | C418: P962FJ | D418: 132.6 | E418: 164.7 | F418: 24.2 | G418: 750.91
A419: 517 | B419: 2025-10-30 | C419: P962FJ | D419: 394.3 | E419: 444 | F419: 12.6 | G419: 1162.85
... A503: 3506 | B503: 2026-09-28 | C503: M908AB | D503: 272.8 | E503: 344.4 | F503: 26.27 | G503: 1676.45
A506: T-08 · Полнота учёта рейса · отклонений: 19 из 3534 проверенных
A507: Рейс | B507: Дата | C507: Статус | D507: Позиций груза | E507: Чего не хватает
A508: 79 | B508: 2025-09-09 | C508: APPROVED | D508: 0 | E508: нет ни одной позиции груза; нет начисления зарплаты
A509: 154 | B509: 2025-09-18 | C509: APPROVED | D509: 0 | E509: нет ни одной позиции груза; нет начисления зарплаты
A510: 364 | B510: 2025-10-11 | C510: APPROVED | D510: 0 | E510: нет ни одной позиции груза; нет начисления зарплаты
A511: 475 | B511: 2025-10-24 | C511: APPROVED | D511: 0 | E511: нет ни одной позиции груза; нет начисления зарплаты
A512: 626 | B512: 2025-11-12 | C512: APPROVED | D512: 0 | E512: нет ни одной позиции груза; нет начисления зарплаты
A513: 902 | B513: 2025-12-13 | C513: APPROVED | D513: 0 | E513: нет ни одной позиции груза; нет начисления зарплаты
A514: 1149 | B514: 2026-01-09 | C514: APPROVED | D514: 0 | E514: нет ни одной позиции груза; нет начисления зарплаты
A515: 1593 | B515: 2026-02-26 | C515: APPROVED | D515: 0 | E515: нет ни одной позиции груза; нет начисления зарплаты
A516: 1848 | B516: 2026-03-26 | C516: APPROVED | D516: 0 | E516: нет ни одной позиции груза; нет начисления зарплаты
A517: 2028 | B517: 2026-04-15 | C517: APPROVED | D517: 0 | E517: нет ни одной позиции груза; нет начисления зарплаты
A518: 2070 | B518: 2026-04-20 | C518: APPROVED | D518: 0 | E518: нет ни одной позиции груза; нет начисления зарплаты
A519: 2098 | B519: 2026-04-22 | C519: APPROVED | D519: 0 | E519: нет ни одной позиции груза; нет начисления зарплаты
... A526: 3316 | B526: 2026-09-05 | C526: APPROVED | D526: 0 | E526: нет ни одной позиции груза; нет начисления зарплаты
A529: T-09 · Хронология исполнения рейса · отклонений: 35 из 3534 проверенных
A530: Рейс | B530: Из статуса | C530: В статус | D530: Характер отклонения
A531: 204 | B531: LOADED | C531: DELIVERED | D531: Пропущена обязательная стадия
A532: 247 | B532: LOADED | C532: DELIVERED | D532: Пропущена обязательная стадия
...

Sheet Выборка
A2: Аудиторская выборка
A3: Для контролей, которые не видны в данных целиком, проверяется выборка документов.
A5: Как сформирована выборка
A6: • Ключ воспроизводимости: «BEMOL-2026». Состав выборки определяется хешем SHA-256 от ключа и номера документа, а не генератором случайных чисел: та же команда на другой машине и в другом году даст тот же список.
A7: • Объём выборки задан шкалой attribute sampling при ожидаемом нулевом уровне отклонений и доверии 90 %: контроль, срабатывающий ежедневно — 25 документов, еженедельно — 5, ежемесячно — 2.
A8: • Одно отклонение в выборке уже означает, что контроль не может быть признан эффективным: нулевой ожидаемый уровень отклонений не допускает исключений.
A10: Контроль | B10: № | C10: Рейс | D10: Дата | E10: Путевой лист | F10: Создал | G10: Утвердил | H10: Результат
A11: FLT-C-10 | B11: 1 | C11: 94 | D11: 2025-09-10 | E11: AP-40094 | F11: dispecer1 | G11: logist1 | H11: Без отклонений
A12: FLT-C-10 | B12: 2 | C12: 95 | D12: 2025-09-11 | E12: AP-40095 | F12: dispecer2 | G12: logist2 | H12: Без отклонений
A13: FLT-C-10 | B13: 3 | C13: 204 | D13: 2025-09-24 | E13: AP-40204 | F13: dispecer1 | G13: logist2 | H13: Без отклонений
A14: FLT-C-10 | B14: 4 | C14: 347 | D14: 2025-10-09 | E14: AP-40347 | F14: dispecer1 | G14: dispecer1 | H14: Отклонение
A15: FLT-C-10 | B15: 5 | C15: 432 | D15: 2025-10-18 | E15: AP-40432 | F15: dispecer1 | G15: dispecer2 | H15: Без отклонений
A16: FLT-C-10 | B16: 6 | C16: 443 | D16: 2025-10-20 | E16: AP-40443 | F16: logist1 | G16: sef.transport | H16: Без отклонений
A17: FLT-C-10 | B17: 7 | C17: 641 | D17: 2025-11-14 | E17: AP-40641 | F17: dispecer1 | G17: sef.transport | H17: Без отклонений
A18: FLT-C-10 | B18: 8 | C18: 698 | D18: 2025-11-20 | E18: AP-40698 | F18: logist1 | G18: dispecer2 | H18: Без отклонений
A19: FLT-C-10 | B19: 9 | C19: 1017 | D19: 2025-12-24 | E19: AP-41017 | F19: dispecer2 | G19: logist1 | H19: Без отклонений
A20: FLT-C-10 | B20: 10 | C20: 1171 | D20: 2026-01-12 | E20: AP-41171 | F20: logist1 | G20: contabil1 | H20: Без отклонений
A21: FLT-C-10 | B21: 11 | C21: 1248 | D21: 2026-01-20 | E21: AP-41248 | F21: logist2 | G21: dispecer2 | H21: Без отклонений
A22: FLT-C-10 | B22: 12 | C22: 1432 | D22: 2026-02-09 | E22: AP-41432 | F22: dispecer1 | G22: dispecer2 | H22: Без отклонений
... A35: FLT-C-10 | B35: 25 | C35: 3392 | D35: 2026-09-16 | E35: AP-43392 | F35: logist1 | G35: logist1 | H35: Отклонение

Sheet Куб
A1: Месяц | B1: Регион | C1: Продукт | D1: Принято, л | E1: Позиций | F1: Потери, л | G1: Оценка потерь, лей | H1: В срезе | I1: В срезе без месяца
A2: 2025-09 | B2: Бэлць | C2: A92 | D2: 213942 | E2: 44 | F2: 1058 | G2: 25603.6 | H2: =IF(AND(OR('Панель BI'!$C$6="Все","сентябрь 2025"='Панель BI'!$C$6),OR('Панель BI'!$F$6="Все",$B2='Панель BI'!$F$6),OR('Панель BI'!$I$6="Все",$C2='Панель BI'!$I$6)),1,0) | I2: =IF(AND(OR('Панель BI'!$F$6="Все",$B2='Панель BI'!$F$6),OR('Панель BI'!$I$6="Все",$C2='Панель BI'!$I$6)),1,0)
A3: 2025-09 | B3: Бэлць | C3: A95 | D3: 159619 | E3: 32 | F3: 381 | G3: 9563.1 | H3: =IF(AND(OR('Панель BI'!$C$6="Все","сентябрь 2025"='Панель BI'!$C$6),OR('Панель BI'!$F$6="Все",$B3='Панель BI'!$F$6),OR('Панель BI'!$I$6="Все",$C3='Панель BI'!$I$6)),1,0) | I3: =IF(AND(OR('Панель BI'!$F$6="Все",$B3='Панель BI'!$F$6),OR('Панель BI'!$I$6="Все",$C3='Панель BI'!$I$6)),1,0)
A4: 2025-09 | B4: Бэлць | C4: DIESEL | D4: 238184 | E4: 49 | F4: 816 | G4: 19094.4 | H4: =IF(AND(OR('Панель BI'!$C$6="Все","сентябрь 2025"='Панель BI'!$C$6),OR('Панель BI'!$F$6="Все",$B4='Панель BI'!$F$6),OR('Панель BI'!$I$6="Все",$C4='Панель BI'!$I$6)),1,0) | I4: =IF(AND(OR('Панель BI'!$F$6="Все",$B4='Панель BI'!$F$6),OR('Панель BI'!$I$6="Все",$C4='Панель BI'!$I$6)),1,0)
A5: 2025-09 | B5: Кагул | C5: A92 | D5: 178446 | E5: 37 | F5: 554 | G5: 13406.8 | H5: =IF(AND(OR('Панель BI'!$C$6="Все","сентябрь 2025"='Панель BI'!$C$6),OR('Панель BI'!$F$6="Все",$B5='Панель BI'!$F$6),OR('Панель BI'!$I$6="Все",$C5='Панель BI'!$I$6)),1,0) | I5: =IF(AND(OR('Панель BI'!$F$6="Все",$B5='Панель BI'!$F$6),OR('Панель BI'!$I$6="Все",$C5='Панель BI'!$I$6)),1,0)
A6: 2025-09 | B6: Кагул | C6: A95 | D6: 182115 | E6: 36 | F6: 885 | G6: 22213.5 | H6: =IF(AND(OR('Панель BI'!$C$6="Все","сентябрь 2025"='Панель BI'!$C$6),OR('Панель BI'!$F$6="Все",$B6='Панель BI'!$F$6),OR('Панель BI'!$I$6="Все",$C6='Панель BI'!$I$6)),1,0) | I6: =IF(AND(OR('Панель BI'!$F$6="Все",$B6='Панель BI'!$F$6),OR('Панель BI'!$I$6="Все",$C6='Панель BI'!$I$6)),1,0)
A7: 2025-09 | B7: Кагул | C7: DIESEL | D7: 162555 | E7: 34 | F7: 445 | G7: 10413 | H7: =IF(AND(OR('Панель BI'!$C$6="Все","сентябрь 2025"='Панель BI'!$C$6),OR('Панель BI'!$F$6="Все",$B7='Панель BI'!$F$6),OR('Панель BI'!$I$6="Все",$C7='Панель BI'!$I$6)),1,0) | I7: =IF(AND(OR('Панель BI'!$F$6="Все",$B7='Панель BI'!$F$6),OR('Панель BI'!$I$6="Все",$C7='Панель BI'!$I$6)),1,0)
A8: 2025-09 | B8: Кишинёв | C8: A92 | D8: 193456 | E8: 39 | F8: 544 | G8: 13164.8 | H8: =IF(AND(OR('Панель BI'!$C$6="Все","сентябрь 2025"='Панель BI'!$C$6),OR('Панель BI'!$F$6="Все",$B8='Панель BI'!$F$6),OR('Панель BI'!$I$6="Все",$C8='Панель BI'!$I$6)),1,0) | I8: =IF(AND(OR('Панель BI'!$F$6="Все",$B8='Панель BI'!$F$6),OR('Панель BI'!$I$6="Все",$C8='Панель BI'!$I$6)),1,0)
A9: 2025-09 | B9: Кишинёв | C9: A95 | D9: 198923 | E9: 41 | F9: 1077 | G9: 27032.7 | H9: =IF(AND(OR('Панель BI'!$C$6="Все","сентябрь 2025"='Панель BI'!$C$6),OR('Панель BI'!$F$6="Все",$B9='Панель BI'!$F$6),OR('Панель BI'!$I$6="Все",$C9='Панель BI'!$I$6)),1,0) | I9: =IF(AND(OR('Панель BI'!$F$6="Все",$B9='Панель BI'!$F$6),OR('Панель BI'!$I$6="Все",$C9='Панель BI'!$I$6)),1,0)
A10: 2025-09 | B10: Кишинёв | C10: DIESEL | D10: 172471 | E10: 34 | F10: 529 | G10: 12378.6 | H10: =IF(AND(OR('Панель BI'!$C$6="Все","сентябрь 2025"='Панель BI'!$C$6),OR('Панель BI'!$F$6="Все",$B10='Панель BI'!$F$6),OR('Панель BI'!$I$6="Все",$C10='Панель BI'!$I$6)),1,0) | I10: =IF(AND(OR('Панель BI'!$F$6="Все",$B10='Панель BI'!$F$6),OR('Панель BI'!$I$6="Все",$C10='Панель BI'!$I$6)),1,0)
A11: 2025-09 | B11: Кишинёв | C11: GPL | D11: 35891 | E11: 8 | F11: 109 | G11: 1504.2 | H11: =IF(AND(OR('Панель BI'!$C$6="Все","сентябрь 2025"='Панель BI'!$C$6),OR('Панель BI'!$F$6="Все",$B11='Панель BI'!$F$6),OR('Панель BI'!$I$6="Все",$C11='Панель BI'!$I$6)),1,0) | I11: =IF(AND(OR('Панель BI'!$F$6="Все",$B11='Панель BI'!$F$6),OR('Панель BI'!$I$6="Все",$C11='Панель BI'!$I$6)),1,0)
A12: 2025-09 | B12: Комрат | C12: A92 | D12: 272061 | E12: 54 | F12: 1110 | G12: 26862 | H12: =IF(AND(OR('Панель BI'!$C$6="Все","сентябрь 2025"='Панель BI'!$C$6),OR('Панель BI'!$F$6="Все",$B12='Панель BI'!$F$6),OR('Панель BI'!$I$6="Все",$C12='Панель BI'!$I$6)),1,0) | I12: =IF(AND(OR('Панель BI'!$F$6="Все",$B12='Панель BI'!$F$6),OR('Панель BI'!$I$6="Все",$C12='Панель BI'!$I$6)),1,0)
A13: 2025-09 | B13: Комрат | C13: A95 | D13: 211426 | E13: 43 | F13: 574 | G13: 14407.4 | H13: =IF(AND(OR('Панель BI'!$C$6="Все","сентябрь 2025"='Панель BI'!$C$6),OR('Панель BI'!$F$6="Все",$B13='Панель BI'!$F$6),OR('Панель BI'!$I$6="Все",$C13='Панель BI'!$I$6)),1,0) | I13: =IF(AND(OR('Панель BI'!$F$6="Все",$B13='Панель BI'!$F$6),OR('Панель BI'!$I$6="Все",$C13='Панель BI'!$I$6)),1,0)
... A22: 2025-09 | B22: Унгень | C22: GPL | D22: 29926 | E22: 6 | F22: 74 | G22: 1021.2 | H22: =IF(AND(OR('Панель BI'!$C$6="Все","сентябрь 2025"='Панель BI'!$C$6),OR('Панель BI'!$F$6="Все",$B22='Панель BI'!$F$6),OR('Панель BI'!$I$6="Все",$C22='Панель BI'!$I$6)),1,0) | I22: =IF(AND(OR('Панель BI'!$F$6="Все",$B22='Панель BI'!$F$6),OR('Панель BI'!$I$6="Все",$C22='Панель BI'!$I$6)),1,0)
A23: 2025-10 | B23: Бэлць | C23: A92 | D23: 170476 | E23: 35 | F23: 524 | G23: 12680.8 | H23: =IF(AND(OR('Панель BI'!$C$6="Все","октябрь 2025"='Панель BI'!$C$6),OR('Панель BI'!$F$6="Все",$B23='Панель BI'!$F$6),OR('Панель BI'!$I$6="Все",$C23='Панель BI'!$I$6)),1,0) | I23: =IF(AND(OR('Панель BI'!$F$6="Все",$B23='Панель BI'!$F$6),OR('Панель BI'!$I$6="Все",$C23='Панель BI'!$I$6)),1,0)
A24: 2025-10 | B24: Бэлць | C24: A95 | D24: 198416 | E24: 39 | F24: 584 | G24: 14658.4 | H24: =IF(AND(OR('Панель BI'!$C$6="Все","октябрь 2025"='Панель BI'!$C$6),OR('Панель BI'!$F$6="Все",$B24='Панель BI'!$F$6),OR('Панель BI'!$I$6="Все",$C24='Панель BI'!$I$6)),1,0) | I24: =IF(AND(OR('Панель BI'!$F$6="Все",$B24='Панель BI'!$F$6),OR('Панель BI'!$I$6="Все",$C24='Панель BI'!$I$6)),1,0)
A25: 2025-10 | B25: Бэлць | C25: DIESEL | D25: 255393 | E25: 51 | F25: 607 | G25: 14203.8 | H25: =IF(AND(OR('Панель BI'!$C$6="Все","октябрь 2025"='Панель BI'!$C$6),OR('Панель BI'!$F$6="Все",$B25='Панель BI'!$F$6),OR('Панель BI'!$I$6="Все",$C25='Панель BI'!$I$6)),1,0) | I25: =IF(AND(OR('Панель BI'!$F$6="Все",$B25='Панель BI'!$F$6),OR('Панель BI'!$I$6="Все",$C25='Панель BI'!$I$6)),1,0)
A26: 2025-10 | B26: Кагул | C26: A92 | D26: 193427 | E26: 39 | F26: 573 | G26: 13866.6 | H26: =IF(AND(OR('Панель BI'!$C$6="Все","октябрь 2025"='Панель BI'!$C$6),OR('Панель BI'!$F$6="Все",$B26='Панель BI'!$F$6),OR('Панель BI'!$I$6="Все",$C26='Панель BI'!$I$6)),1,0) | I26: =IF(AND(OR('Панель BI'!$F$6="Все",$B26='Панель BI'!$F$6),OR('Панель BI'!$I$6="Все",$C26='Панель BI'!$I$6)),1,0)
A27: 2025-10 | B27: Кагул | C27: A95 | D27: 198065 | E27: 41 | F27: 935 | G27: 23468.5 | H27: =IF(AND(OR('Панель BI'!$C$6="Все","октябрь 2025"='Панель BI'!$C$6),OR('Панель BI'!$F$6="Все",$B27='Панель BI'!$F$6),OR('Панель BI'!$I$6="Все",$C27='Панель BI'!$I$6)),1,0) | I27: =IF(AND(OR('Панель BI'!$F$6="Все",$B27='Панель BI'!$F$6),OR('Панель BI'!$I$6="Все",$C27='Панель BI'!$I$6)),1,0)
A28: 2025-10 | B28: Кагул | C28: DIESEL | D28: 205575 | E28: 44 | F28: 1425 | G28: 33345 | H28: =IF(AND(OR('Панель BI'!$C$6="Все","октябрь 2025"='Панель BI'!$C$6),OR('Панель BI'!$F$6="Все",$B28='Панель BI'!$F$6),OR('Панель BI'!$I$6="Все",$C28='Панель BI'!$I$6)),1,0) | I28: =IF(AND(OR('Панель BI'!$F$6="Все",$B28='Панель BI'!$F$6),OR('Панель BI'!$I$6="Все",$C28='Панель BI'!$I$6)),1,0)
A29: 2025-10 | B29: Кишинёв | C29: A92 | D29: 210397 | E29: 42 | F29: 603 | G29: 14592.6 | H29: =IF(AND(OR('Панель BI'!$C$6="Все","октябрь 2025"='Панель BI'!$C$6),OR('Панель BI'!$F$6="Все",$B29='Панель BI'!$F$6),OR('Панель BI'!$I$6="Все",$C29='Панель BI'!$I$6)),1,0) | I29: =IF(AND(OR('Панель BI'!$F$6="Все",$B29='Панель BI'!$F$6),OR('Панель BI'!$I$6="Все",$C29='Панель BI'!$I$6)),1,0)
A30: 2025-10 | B30: Кишинёв | C30: A95 | D30: 202395 | E30: 39 | F30: 605 | G30: 15185.5 | H30: =IF(AND(OR('Панель BI'!$C$6="Все","октябрь 2025"='Панель BI'!$C$6),OR('Панель BI'!$F$6="Все",$B30='Панель BI'!$F$6),OR('Панель BI'!$I$6="Все",$C30='Панель BI'!$I$6)),1,0) | I30: =IF(AND(OR('Панель BI'!$F$6="Все",$B30='Панель BI'!$F$6),OR('Панель BI'!$I$6="Все",$C30='Панель BI'!$I$6)),1,0)
A31: 2025-10 | B31: Кишинёв | C31: DIESEL | D31: 201471 | E31: 40 | F31: 529 | G31: 12378.6 | H31: =IF(AND(OR('Панель BI'!$C$6="Все","октябрь 2025"='Панель BI'!$C$6),OR('Панель BI'!$F$6="Все",$B31='Панель BI'!$F$6),OR('Панель BI'!$I$6="Все",$C31='Панель BI'!$I$6)),1,0) | I31: =IF(AND(OR('Панель BI'!$F$6="Все",$B31='Панель BI'!$F$6),OR('Панель BI'!$I$6="Все",$C31='Панель BI'!$I$6)),1,0)
A32: 2025-10 | B32: Кишинёв | C32: GPL | D32: 41866 | E32: 8 | F32: 134 | G32: 1849.2 | H32: =IF(AND(OR('Панель BI'!$C$6="Все","октябрь 2025"='Панель BI'!$C$6),OR('Панель BI'!$F$6="Все",$B32='Панель BI'!$F$6),OR('Панель BI'!$I$6="Все",$C32='Панель BI'!$I$6)),1,0) | I32: =IF(AND(OR('Панель BI'!$F$6="Все",$B32='Панель BI'!$F$6),OR('Панель BI'!$I$6="Все",$C32='Панель BI'!$I$6)),1,0)
A33: 2025-10 | B33: Комрат | C33: A92 | D33: 184470 | E33: 37 | F33: 530 | G33: 12826 | H33: =IF(AND(OR('Панель BI'!$C$6="Все","октябрь 2025"='Панель BI'!$C$6),OR('Панель BI'!$F$6="Все",$B33='Панель BI'!$F$6),OR('Панель BI'!$I$6="Все",$C33='Панель BI'!$I$6)),1,0) | I33: =IF(AND(OR('Панель BI'!$F$6="Все",$B33='Панель BI'!$F$6),OR('Панель BI'!$I$6="Все",$C33='Панель BI'!$I$6)),1,0)
A34: 2025-10 | B34: Комрат | C34: A95 | D34: 237070 | E34: 49 | F34: 930 | G34: 23343 | H34: =IF(AND(OR('Панель BI'!$C$6="Все","октябрь 2025"='Панель BI'!$C$6),OR('Панель BI'!$F$6="Все",$B34='Панель BI'!$F$6),OR('Панель BI'!$I$6="Все",$C34='Панель BI'!$I$6)),1,0) | I34: =IF(AND(OR('Панель BI'!$F$6="Все",$B34='Панель BI'!$F$6),OR('Панель BI'!$I$6="Все",$C34='Панель BI'!$I$6)),1,0)
... A43: 2025-10 | B43: Унгень | C43: GPL | D43: 38910 | E43: 8 | F43: 90 | G43: 1242 | H43: =IF(AND(OR('Панель BI'!$C$6="Все","октябрь 2025"='Панель BI'!$C$6),OR('Панель BI'!$F$6="Все",$B43='Панель BI'!$F$6),OR('Панель BI'!$I$6="Все",$C43='Панель BI'!$I$6)),1,0) | I43: =IF(AND(OR('Панель BI'!$F$6="Все",$B43='Панель BI'!$F$6),OR('Панель BI'!$I$6="Все",$C43='Панель BI'!$I$6)),1,0)
A44: 2025-11 | B44: Бэлць | C44: A92 | D44: 226216 | E44: 46 | F44: 784 | G44: 18972.8 | H44: =IF(AND(OR('Панель BI'!$C$6="Все","ноябрь 2025"='Панель BI'!$C$6),OR('Панель BI'!$F$6="Все",$B44='Панель BI'!$F$6),OR('Панель BI'!$I$6="Все",$C44='Панель BI'!$I$6)),1,0) | I44: =IF(AND(OR('Панель BI'!$F$6="Все",$B44='Панель BI'!$F$6),OR('Панель BI'!$I$6="Все",$C44='Панель BI'!$I$6)),1,0)
A45: 2025-11 | B45: Бэлць | C45: A95 | D45: 232276 | E45: 48 | F45: 724 | G45: 18172.4 | H45: =IF(AND(OR('Панель BI'!$C$6="Все","ноябрь 2025"='Панель BI'!$C$6),OR('Панель BI'!$F$6="Все",$B45='Панель BI'!$F$6),OR('Панель BI'!$I$6="Все",$C45='Панель BI'!$I$6)),1,0) | I45: =IF(AND(OR('Панель BI'!$F$6="Все",$B45='Панель BI'!$F$6),OR('Панель BI'!$I$6="Все",$C45='Панель BI'!$I$6)),1,0)
A46: 2025-11 | B46: Бэлць | C46: DIESEL | D46: 240191 | E46: 48 | F46: 809 | G46: 18930.6 | H46: =IF(AND(OR('Панель BI'!$C$6="Все","ноябрь 2025"='Панель BI'!$C$6),OR('Панель BI'!$F$6="Все",$B46='Панель BI'!$F$6),OR('Панель BI'!$I$6="Все",$C46='Панель BI'!$I$6)),1,0) | I46: =IF(AND(OR('Панель BI'!$F$6="Все",$B46='Панель BI'!$F$6),OR('Панель BI'!$I$6="Все",$C46='Панель BI'!$I$6)),1,0)
A47: 2025-11 | B47: Кагул | C47: A92 | D47: 176549 | E47: 36 | F47: 451 | G47: 10914.2 | H47: =IF(AND(OR('Панель BI'!$C$6="Все","ноябрь 2025"='Панель BI'!$C$6),OR('Панель BI'!$F$6="Все",$B47='Панель BI'!$F$6),OR('Панель BI'!$I$6="Все",$C47='Панель BI'!$I$6)),1,0) | I47: =IF(AND(OR('Панель BI'!$F$6="Все",$B47='Панель BI'!$F$6),OR('Панель BI'!$I$6="Все",$C47='Панель BI'!$I$6)),1,0)
A48: 2025-11 | B48: Кагул | C48: A95 | D48: 169561 | E48: 33 | F48: 439 | G48: 11018.9 | H48: =IF(AND(OR('Панель BI'!$C$6="Все","ноябрь 2025"='Панель BI'!$C$6),OR('Панель BI'!$F$6="Все",$B48='Панель BI'!$F$6),OR('Панель BI'!$I$6="Все",$C48='Панель BI'!$I$6)),1,0) | I48: =IF(AND(OR('Панель BI'!$F$6="Все",$B48='Панель BI'!$F$6),OR('Панель BI'!$I$6="Все",$C48='Панель BI'!$I$6)),1,0)
A49: 2025-11 | B49: Кагул | C49: DIESEL | D49: 225079 | E49: 44 | F49: 921 | G49: 21551.4 | H49: =IF(AND(OR('Панель BI'!$C$6="Все","ноябрь 2025"='Панель BI'!$C$6),OR('Панель BI'!$F$6="Все",$B49='Панель BI'!$F$6),OR('Панель BI'!$I$6="Все",$C49='Панель BI'!$I$6)),1,0) | I49: =IF(AND(OR('Панель BI'!$F$6="Все",$B49='Панель BI'!$F$6),OR('Панель BI'!$I$6="Все",$C49='Панель BI'!$I$6)),1,0)
A50: 2025-11 | B50: Кишинёв | C50: A92 | D50: 146590 | E50: 30 | F50: 410 | G50: 9922 | H50: =IF(AND(OR('Панель BI'!$C$6="Все","ноябрь 2025"='Панель BI'!$C$6),OR('Панель BI'!$F$6="Все",$B50='Панель BI'!$F$6),OR('Панель BI'!$I$6="Все",$C50='Панель BI'!$I$6)),1,0) | I50: =IF(AND(OR('Панель BI'!$F$6="Все",$B50='Панель BI'!$F$6),OR('Панель BI'!$I$6="Все",$C50='Панель BI'!$I$6)),1,0)
A51: 2025-11 | B51: Кишинёв | C51: A95 | D51: 192351 | E51: 38 | F51: 649 | G51: 16289.9 | H51: =IF(AND(OR('Панель BI'!$C$6="Все","ноябрь 2025"='Панель BI'!$C$6),OR('Панель BI'!$F$6="Все",$B51='Панель BI'!$F$6),OR('Панель BI'!$I$6="Все",$C51='Панель BI'!$I$6)),1,0) | I51: =IF(AND(OR('Панель BI'!$F$6="Все",$B51='Панель BI'!$F$6),OR('Панель BI'!$I$6="Все",$C51='Панель BI'!$I$6)),1,0)
A52: 2025-11 | B52: Кишинёв | C52: DIESEL | D52: 240336 | E52: 47 | F52: 664 | G52: 15537.6 | H52: =IF(AND(OR('Панель BI'!$C$6="Все","ноябрь 2025"='Панель BI'!$C$6),OR('Панель BI'!$F$6="Все",$B52='Панель BI'!$F$6),OR('Панель BI'!$I$6="Все",$C52='Панель BI'!$I$6)),1,0) | I52: =IF(AND(OR('Панель BI'!$F$6="Все",$B52='Панель BI'!$F$6),OR('Панель BI'!$I$6="Все",$C52='Панель BI'!$I$6)),1,0)
A53: 2025-11 | B53: Кишинёв | C53: GPL | D53: 66774 | E53: 14 | F53: 226 | G53: 3118.8 | H53: =IF(AND(OR('Панель BI'!$C$6="Все","ноябрь 2025"='Панель BI'!$C$6),OR('Панель BI'!$F$6="Все",$B53='Панель BI'!$F$6),OR('Панель BI'!$I$6="Все",$C53='Панель BI'!$I$6)),1,0) | I53: =IF(AND(OR('Панель BI'!$F$6="Все",$B53='Панель BI'!$F$6),OR('Панель BI'!$I$6="Все",$C53='Панель BI'!$I$6)),1,0)
A54: 2025-11 | B54: Комрат | C54: A92 | D54: 157529 | E54: 32 | F54: 471 | G54: 11398.2 | H54: =IF(AND(OR('Панель BI'!$C$6="Все","ноябрь 2025"='Панель BI'!$C$6),OR('Панель BI'!$F$6="Все",$B54='Панель BI'!$F$6),OR('Панель BI'!$I$6="Все",$C54='Панель BI'!$I$6)),1,0) | I54: =IF(AND(OR('Панель BI'!$F$6="Все",$B54='Панель BI'!$F$6),OR('Панель BI'!$I$6="Все",$C54='Панель BI'!$I$6)),1,0)
A55: 2025-11 | B55: Комрат | C55: A95 | D55: 162429 | E55: 33 | F55: 571 | G55: 14332.1 | H55: =IF(AND(OR('Панель BI'!$C$6="Все","ноябрь 2025"='Панель BI'!$C$6),OR('Панель BI'!$F$6="Все",$B55='Панель BI'!$F$6),OR('Панель BI'!$I$6="Все",$C55='Панель BI'!$I$6)),1,0) | I55: =IF(AND(OR('Панель BI'!$F$6="Все",$B55='Панель BI'!$F$6),OR('Панель BI'!$I$6="Все",$C55='Панель BI'!$I$6)),1,0)
... A64: 2025-11 | B64: Унгень | C64: GPL | D64: 56827 | E64: 11 | F64: 173 | G64: 2387.4 | H64: =IF(AND(OR('Панель BI'!$C$6="Все","ноябрь 2025"='Панель BI'!$C$6),OR('Панель BI'!$F$6="Все",$B64='Панель BI'!$F$6),OR('Панель BI'!$I$6="Все",$C64='Панель BI'!$I$6)),1,0) | I64: =IF(AND(OR('Панель BI'!$F$6="Все",$B64='Панель BI'!$F$6),OR('Панель BI'!$I$6="Все",$C64='Панель BI'!$I$6)),1,0)
A65: 2025-12 | B65: Бэлць | C65: A92 | D65: 234386 | E65: 49 | F65: 614 | G65: 14858.8 | H65: =IF(AND(OR('Панель BI'!$C$6="Все","декабрь 2025"='Панель BI'!$C$6),OR('Панель BI'!$F$6="Все",$B65='Панель BI'!$F$6),OR('Панель BI'!$I$6="Все",$C65='Панель BI'!$I$6)),1,0) | I65: =IF(AND(OR('Панель BI'!$F$6="Все",$B65='Панель BI'!$F$6),OR('Панель BI'!$I$6="Все",$C65='Панель BI'!$I$6)),1,0)
A66: 2025-12 | B66: Бэлць | C66: A95 | D66: 223960 | E66: 45 | F66: 1040 | G66: 26104 | H66: =IF(AND(OR('Панель BI'!$C$6="Все","декабрь 2025"='Панель BI'!$C$6),OR('Панель BI'!$F$6="Все",$B66='Панель BI'!$F$6),OR('Панель BI'!$I$6="Все",$C66='Панель BI'!$I$6)),1,0) | I66: =IF(AND(OR('Панель BI'!$F$6="Все",$B66='Панель BI'!$F$6),OR('Панель BI'!$I$6="Все",$C66='Панель BI'!$I$6)),1,0)
A67: 2025-12 | B67: Бэлць | C67: DIESEL | D67: 230346 | E67: 46 | F67: 654 | G67: 15303.6 | H67: =IF(AND(OR('Панель BI'!$C$6="Все","декабрь 2025"='Панель BI'!$C$6),OR('Панель BI'!$F$6="Все",$B67='Панель BI'!$F$6),OR('Панель BI'!$I$6="Все",$C67='Панель BI'!$I$6)),1,0) | I67: =IF(AND(OR('Панель BI'!$F$6="Все",$B67='Панель BI'!$F$6),OR('Панель BI'!$I$6="Все",$C67='Панель BI'!$I$6)),1,0)
A68: 2025-12 | B68: Кагул | C68: A92 | D68: 247851 | E68: 49 | F68: 1149 | G68: 27805.8 | H68: =IF(AND(OR('Панель BI'!$C$6="Все","декабрь 2025"='Панель BI'!$C$6),OR('Панель BI'!$F$6="Все",$B68='Панель BI'!$F$6),OR('Панель BI'!$I$6="Все",$C68='Панель BI'!$I$6)),1,0) | I68: =IF(AND(OR('Панель BI'!$F$6="Все",$B68='Панель BI'!$F$6),OR('Панель BI'!$I$6="Все",$C68='Панель BI'!$I$6)),1,0)
A69: 2025-12 | B69: Кагул | C69: A95 | D69: 223909 | E69: 45 | F69: 1091 | G69: 27384.1 | H69: =IF(AND(OR('Панель BI'!$C$6="Все","декабрь 2025"='Панель BI'!$C$6),OR('Панель BI'!$F$6="Все",$B69='Панель BI'!$F$6),OR('Панель BI'!$I$6="Все",$C69='Панель BI'!$I$6)),1,0) | I69: =IF(AND(OR('Панель BI'!$F$6="Все",$B69='Панель BI'!$F$6),OR('Панель BI'!$I$6="Все",$C69='Панель BI'!$I$6)),1,0)
A70: 2025-12 | B70: Кагул | C70: DIESEL | D70: 214279 | E70: 43 | F70: 721 | G70: 16871.4 | H70: =IF(AND(OR('Панель BI'!$C$6="Все","декабрь 2025"='Панель BI'!$C$6),OR('Панель BI'!$F$6="Все",$B70='Панель BI'!$F$6),OR('Панель BI'!$I$6="Все",$C70='Панель BI'!$I$6)),1,0) | I70: =IF(AND(OR('Панель BI'!$F$6="Все",$B70='Панель BI'!$F$6),OR('Панель BI'!$I$6="Все",$C70='Панель BI'!$I$6)),1,0)
A71: 2025-12 | B71: Кишинёв | C71: A92 | D71: 263579 | E71: 50 | F71: 694 | G71: 16794.8 | H71: =IF(AND(OR('Панель BI'!$C$6="Все","декабрь 2025"='Панель BI'!$C$6),OR('Панель BI'!$F$6="Все",$B71='Панель BI'!$F$6),OR('Панель BI'!$I$6="Все",$C71='Панель BI'!$I$6)),1,0) | I71: =IF(AND(OR('Панель BI'!$F$6="Все",$B71='Панель BI'!$F$6),OR('Панель BI'!$I$6="Все",$C71='Панель BI'!$I$6)),1,0)
A72: 2025-12 | B72: Кишинёв | C72: A95 | D72: 264266 | E72: 54 | F72: 734 | G72: 18423.4 | H72: =IF(AND(OR('Панель BI'!$C$6="Все","декабрь 2025"='Панель BI'!$C$6),OR('Панель BI'!$F$6="Все",$B72='Панель BI'!$F$6),OR('Панель BI'!$I$6="Все",$C72='Панель BI'!$I$6)),1,0) | I72: =IF(AND(OR('Панель BI'!$F$6="Все",$B72='Панель BI'!$F$6),OR('Панель BI'!$I$6="Все",$C72='Панель BI'!$I$6)),1,0)
A73: 2025-12 | B73: Кишинёв | C73: DIESEL | D73: 178024 | E73: 36 | F73: 976 | G73: 22838.4 | H73: =IF(AND(OR('Панель BI'!$C$6="Все","декабрь 2025"='Панель BI'!$C$6),OR('Панель BI'!$F$6="Все",$B73='Панель BI'!$F$6),OR('Панель BI'!$I$6="Все",$C73='Панель BI'!$I$6)),1,0) | I73: =IF(AND(OR('Панель BI'!$F$6="Все",$B73='Панель BI'!$F$6),OR('Панель BI'!$I$6="Все",$C73='Панель BI'!$I$6)),1,0)
A74: 2025-12 | B74: Кишинёв | C74: GPL | D74: 64824 | E74: 13 | F74: 176 | G74: 2428.8 | H74: =IF(AND(OR('Панель BI'!$C$6="Все","декабрь 2025"='Панель BI'!$C$6),OR('Панель BI'!$F$6="Все",$B74='Панель BI'!$F$6),OR('Панель BI'!$I$6="Все",$C74='Панель BI'!$I$6)),1,0) | I74: =IF(AND(OR('Панель BI'!$F$6="Все",$B74='Панель BI'!$F$6),OR('Панель BI'!$I$6="Все",$C74='Панель BI'!$I$6)),1,0)
A75: 2025-12 | B75: Комрат | C75: A92 | D75: 257212 | E75: 52 | F75: 788 | G75: 19069.6 | H75: =IF(AND(OR('Панель BI'!$C$6="Все","декабрь 2025"='Панель BI'!$C$6),OR('Панель BI'!$F$6="Все",$B75='Панель BI'!$F$6),OR('Панель BI'!$I$6="Все",$C75='Панель BI'!$I$6)),1,0) | I75: =IF(AND(OR('Панель BI'!$F$6="Все",$B75='Панель BI'!$F$6),OR('Панель BI'!$I$6="Все",$C75='Панель BI'!$I$6)),1,0)
A76: 2025-12 | B76: Комрат | C76: A95 | D76: 223273 | E76: 47 | F76: 727 | G76: 18247.7 | H76: =IF(AND(OR('Панель BI'!$C$6="Все","декабрь 2025"='Панель BI'!$C$6),OR('Панель BI'!$F$6="Все",$B76='Панель BI'!$F$6),OR('Панель BI'!$I$6="Все",$C76='Панель BI'!$I$6)),1,0) | I76: =IF(AND(OR('Панель BI'!$F$6="Все",$B76='Панель BI'!$F$6),OR('Панель BI'!$I$6="Все",$C76='Панель BI'!$I$6)),1,0)
... A85: 2025-12 | B85: Унгень | C85: GPL | D85: 74820 | E85: 14 | F85: 180 | G85: 2484 | H85: =IF(AND(OR('Панель BI'!$C$6="Все","декабрь 2025"='Панель BI'!$C$6),OR('Панель BI'!$F$6="Все",$B85='Панель BI'!$F$6),OR('Панель BI'!$I$6="Все",$C85='Панель BI'!$I$6)),1,0) | I85: =IF(AND(OR('Панель BI'!$F$6="Все",$B85='Панель BI'!$F$6),OR('Панель BI'!$I$6="Все",$C85='Панель BI'!$I$6)),1,0)
A86: 2026-01 | B86: Бэлць | C86: A92 | D86: 192435 | E86: 39 | F86: 565 | G86: 13673 | H86: =IF(AND(OR('Панель BI'!$C$6="Все","январь 2026"='Панель BI'!$C$6),OR('Панель BI'!$F$6="Все",$B86='Панель BI'!$F$6),OR('Панель BI'!$I$6="Все",$C86='Панель BI'!$I$6)),1,0) | I86: =IF(AND(OR('Панель BI'!$F$6="Все",$B86='Панель BI'!$F$6),OR('Панель BI'!$I$6="Все",$C86='Панель BI'!$I$6)),1,0)
A87: 2026-01 | B87: Бэлць | C87: A95 | D87: 176218 | E87: 36 | F87: 782 | G87: 19628.2 | H87: =IF(AND(OR('Панель BI'!$C$6="Все","январь 2026"='Панель BI'!$C$6),OR('Панель BI'!$F$6="Все",$B87='Панель BI'!$F$6),OR('Панель BI'!$I$6="Все",$C87='Панель BI'!$I$6)),1,0) | I87: =IF(AND(OR('Панель BI'!$F$6="Все",$B87='Панель BI'!$F$6),OR('Панель BI'!$I$6="Все",$C87='Панель BI'!$I$6)),1,0)
A88: 2026-01 | B88: Бэлць | C88: DIESEL | D88: 210493 | E88: 44 | F88: 507 | G88: 11863.8 | H88: =IF(AND(OR('Панель BI'!$C$6="Все","январь 2026"='Панель BI'!$C$6),OR('Панель BI'!$F$6="Все",$B88='Панель BI'!$F$6),OR('Панель BI'!$I$6="Все",$C88='Панель BI'!$I$6)),1,0) | I88: =IF(AND(OR('Панель BI'!$F$6="Все",$B88='Панель BI'!$F$6),OR('Панель BI'!$I$6="Все",$C88='Панель BI'!$I$6)),1,0)
A89: 2026-01 | B89: Кагул | C89: A92 | D89: 200439 | E89: 42 | F89: 561 | G89: 13576.2 | H89: =IF(AND(OR('Панель BI'!$C$6="Все","январь 2026"='Панель BI'!$C$6),OR('Панель BI'!$F$6="Все",$B89='Панель BI'!$F$6),OR('Панель BI'!$I$6="Все",$C89='Панель BI'!$I$6)),1,0) | I89: =IF(AND(OR('Панель BI'!$F$6="Все",$B89='Панель BI'!$F$6),OR('Панель BI'!$I$6="Все",$C89='Панель BI'!$I$6)),1,0)
A90: 2026-01 | B90: Кагул | C90: A95 | D90: 222265 | E90: 44 | F90: 735 | G90: 18448.5 | H90: =IF(AND(OR('Панель BI'!$C$6="Все","январь 2026"='Панель BI'!$C$6),OR('Панель BI'!$F$6="Все",$B90='Панель BI'!$F$6),OR('Панель BI'!$I$6="Все",$C90='Панель BI'!$I$6)),1,0) | I90: =IF(AND(OR('Панель BI'!$F$6="Все",$B90='Панель BI'!$F$6),OR('Панель BI'!$I$6="Все",$C90='Панель BI'!$I$6)),1,0)
A91: 2026-01 | B91: Кагул | C91: DIESEL | D91: 174504 | E91: 36 | F91: 496 | G91: 11606.4 | H91: =IF(AND(OR('Панель BI'!$C$6="Все","январь 2026"='Панель BI'!$C$6),OR('Панель BI'!$F$6="Все",$B91='Панель BI'!$F$6),OR('Панель BI'!$I$6="Все",$C91='Панель BI'!$I$6)),1,0) | I91: =IF(AND(OR('Панель BI'!$F$6="Все",$B91='Панель BI'!$F$6),OR('Панель BI'!$I$6="Все",$C91='Панель BI'!$I$6)),1,0)
A92: 2026-01 | B92: Кишинёв | C92: A92 | D92: 262024 | E92: 52 | F92: 976 | G92: 23619.2 | H92: =IF(AND(OR('Панель BI'!$C$6="Все","январь 2026"='Панель BI'!$C$6),OR('Панель BI'!$F$6="Все",$B92='Панель BI'!$F$6),OR('Панель BI'!$I$6="Все",$C92='Панель BI'!$I$6)),1,0) | I92: =IF(AND(OR('Панель BI'!$F$6="Все",$B92='Панель BI'!$F$6),OR('Панель BI'!$I$6="Все",$C92='Панель BI'!$I$6)),1,0)
A93: 2026-01 | B93: Кишинёв | C93: A95 | D93: 224300 | E93: 44 | F93: 700 | G93: 17570 | H93: =IF(AND(OR('Панель BI'!$C$6="Все","январь 2026"='Панель BI'!$C$6),OR('Панель BI'!$F$6="Все",$B93='Панель BI'!$F$6),OR('Панель BI'!$I$6="Все",$C93='Панель BI'!$I$6)),1,0) | I93: =IF(AND(OR('Панель BI'!$F$6="Все",$B93='Панель BI'!$F$6),OR('Панель BI'!$I$6="Все",$C93='Панель BI'!$I$6)),1,0)
A94: 2026-01 | B94: Кишинёв | C94: DIESEL | D94: 258871 | E94: 51 | F94: 1129 | G94: 26418.6 | H94: =IF(AND(OR('Панель BI'!$C$6="Все","январь 2026"='Панель BI'!$C$6),OR('Панель BI'!$F$6="Все",$B94='Панель BI'!$F$6),OR('Панель BI'!$I$6="Все",$C94='Панель BI'!$I$6)),1,0) | I94: =IF(AND(OR('Панель BI'!$F$6="Все",$B94='Панель BI'!$F$6),OR('Панель BI'!$I$6="Все",$C94='Панель BI'!$I$6)),1,0)
A95: 2026-01 | B95: Кишинёв | C95: GPL | D95: 46879 | E95: 9 | F95: 121 | G95: 1669.8 | H95: =IF(AND(OR('Панель BI'!$C$6="Все","январь 2026"='Панель BI'!$C$6),OR('Панель BI'!$F$6="Все",$B95='Панель BI'!$F$6),OR('Панель BI'!$I$6="Все",$C95='Панель BI'!$I$6)),1,0) | I95: =IF(AND(OR('Панель BI'!$F$6="Все",$B95='Панель BI'!$F$6),OR('Панель BI'!$I$6="Все",$C95='Панель BI'!$I$6)),1,0)
A96: 2026-01 | B96: Комрат | C96: A92 | D96: 249997 | E96: 51 | F96: 1003 | G96: 24272.6 | H96: =IF(AND(OR('Панель BI'!$C$6="Все","январь 2026"='Панель BI'!$C$6),OR('Панель BI'!$F$6="Все",$B96='Панель BI'!$F$6),OR('Панель BI'!$I$6="Все",$C96='Панель BI'!$I$6)),1,0) | I96: =IF(AND(OR('Панель BI'!$F$6="Все",$B96='Панель BI'!$F$6),OR('Панель BI'!$I$6="Все",$C96='Панель BI'!$I$6)),1,0)
A97: 2026-01 | B97: Комрат | C97: A95 | D97: 291343 | E97: 57 | F97: 1393 | G97: 34964.3 | H97: =IF(AND(OR('Панель BI'!$C$6="Все","январь 2026"='Панель BI'!$C$6),OR('Панель BI'!$F$6="Все",$B97='Панель BI'!$F$6),OR('Панель BI'!$I$6="Все",$C97='Панель BI'!$I$6)),1,0) | I97: =IF(AND(OR('Панель BI'!$F$6="Все",$B97='Панель BI'!$F$6),OR('Панель BI'!$I$6="Все",$C97='Панель BI'!$I$6)),1,0)
... A106: 2026-01 | B106: Унгень | C106: GPL | D106: 64849 | E106: 12 | F106: 151 | G106: 2083.8 | H106: =IF(AND(OR('Панель BI'!$C$6="Все","январь 2026"='Панель BI'!$C$6),OR('Панель BI'!$F$6="Все",$B106='Панель BI'!$F$6),OR('Панель BI'!$I$6="Все",$C106='Панель BI'!$I$6)),1,0) | I106: =IF(AND(OR('Панель BI'!$F$6="Все",$B106='Панель BI'!$F$6),OR('Панель BI'!$I$6="Все",$C106='Панель BI'!$I$6)),1,0)
A107: 2026-02 | B107: Бэлць | C107: A92 | D107: 188767 | E107: 38 | F107: 583 | G107: 14108.6 | H107: =IF(AND(OR('Панель BI'!$C$6="Все","февраль 2026"='Панель BI'!$C$6),OR('Панель BI'!$F$6="Все",$B107='Панель BI'!$F$6),OR('Панель BI'!$I$6="Все",$C107='Панель BI'!$I$6)),1,0) | I107: =IF(AND(OR('Панель BI'!$F$6="Все",$B107='Панель BI'!$F$6),OR('Панель BI'!$I$6="Все",$C107='Панель BI'!$I$6)),1,0)
A108: 2026-02 | B108: Бэлць | C108: A95 | D108: 183590 | E108: 37 | F108: 1410 | G108: 35391 | H108: =IF(AND(OR('Панель BI'!$C$6="Все","февраль 2026"='Панель BI'!$C$6),OR('Панель BI'!$F$6="Все",$B108='Панель BI'!$F$6),OR('Панель BI'!$I$6="Все",$C108='Панель BI'!$I$6)),1,0) | I108: =IF(AND(OR('Панель BI'!$F$6="Все",$B108='Панель BI'!$F$6),OR('Панель BI'!$I$6="Все",$C108='Панель BI'!$I$6)),1,0)
A109: 2026-02 | B109: Бэлць | C109: DIESEL | D109: 243249 | E109: 50 | F109: 751 | G109: 17573.4 | H109: =IF(AND(OR('Панель BI'!$C$6="Все","февраль 2026"='Панель BI'!$C$6),OR('Панель BI'!$F$6="Все",$B109='Панель BI'!$F$6),OR('Панель BI'!$I$6="Все",$C109='Панель BI'!$I$6)),1,0) | I109: =IF(AND(OR('Панель BI'!$F$6="Все",$B109='Панель BI'!$F$6),OR('Панель BI'!$I$6="Все",$C109='Панель BI'!$I$6)),1,0)
A110: 2026-02 | B110: Кагул | C110: A92 | D110: 204025 | E110: 41 | F110: 975 | G110: 23595 | H110: =IF(AND(OR('Панель BI'!$C$6="Все","февраль 2026"='Панель BI'!$C$6),OR('Панель BI'!$F$6="Все",$B110='Панель BI'!$F$6),OR('Панель BI'!$I$6="Все",$C110='Панель BI'!$I$6)),1,0) | I110: =IF(AND(OR('Панель BI'!$F$6="Все",$B110='Панель BI'!$F$6),OR('Панель BI'!$I$6="Все",$C110='Панель BI'!$I$6)),1,0)
A111: 2026-02 | B111: Кагул | C111: A95 | D111: 161172 | E111: 32 | F111: 828 | G111: 20782.8 | H111: =IF(AND(OR('Панель BI'!$C$6="Все","февраль 2026"='Панель BI'!$C$6),OR('Панель BI'!$F$6="Все",$B111='Панель BI'!$F$6),OR('Панель BI'!$I$6="Все",$C111='Панель BI'!$I$6)),1,0) | I111: =IF(AND(OR('Панель BI'!$F$6="Все",$B111='Панель BI'!$F$6),OR('Панель BI'!$I$6="Все",$C111='Панель BI'!$I$6)),1,0)
A112: 2026-02 | B112: Кагул | C112: DIESEL | D112: 176457 | E112: 34 | F112: 543 | G112: 12706.2 | H112: =IF(AND(OR('Панель BI'!$C$6="Все","февраль 2026"='Панель BI'!$C$6),OR('Панель BI'!$F$6="Все",$B112='Панель BI'!$F$6),OR('Панель BI'!$I$6="Все",$C112='Панель BI'!$I$6)),1,0) | I112: =IF(AND(OR('Панель BI'!$F$6="Все",$B112='Панель BI'!$F$6),OR('Панель BI'!$I$6="Все",$C112='Панель BI'!$I$6)),1,0)
A113: 2026-02 | B113: Кишинёв | C113: A92 | D113: 258763 | E113: 52 | F113: 1237 | G113: 29935.4 | H113: =IF(AND(OR('Панель BI'!$C$6="Все","февраль 2026"='Панель BI'!$C$6),OR('Панель BI'!$F$6="Все",$B113='Панель BI'!$F$6),OR('Панель BI'!$I$6="Все",$C113='Панель BI'!$I$6)),1,0) | I113: =IF(AND(OR('Панель BI'!$F$6="Все",$B113='Панель BI'!$F$6),OR('Панель BI'!$I$6="Все",$C113='Панель BI'!$I$6)),1,0)
A114: 2026-02 | B114: Кишинёв | C114: A95 | D114: 170509 | E114: 33 | F114: 491 | G114: 12324.1 | H114: =IF(AND(OR('Панель BI'!$C$6="Все","февраль 2026"='Панель BI'!$C$6),OR('Панель BI'!$F$6="Все",$B114='Панель BI'!$F$6),OR('Панель BI'!$I$6="Все",$C114='Панель BI'!$I$6)),1,0) | I114: =IF(AND(OR('Панель BI'!$F$6="Все",$B114='Панель BI'!$F$6),OR('Панель BI'!$I$6="Все",$C114='Панель BI'!$I$6)),1,0)
A115: 2026-02 | B115: Кишинёв | C115: DIESEL | D115: 199430 | E115: 41 | F115: 570 | G115: 13338 | H115: =IF(AND(OR('Панель BI'!$C$6="Все","февраль 2026"='Панель BI'!$C$6),OR('Панель BI'!$F$6="Все",$B115='Панель BI'!$F$6),OR('Панель BI'!$I$6="Все",$C115='Панель BI'!$I$6)),1,0) | I115: =IF(AND(OR('Панель BI'!$F$6="Все",$B115='Панель BI'!$F$6),OR('Панель BI'!$I$6="Все",$C115='Панель BI'!$I$6)),1,0)
A116: 2026-02 | B116: Кишинёв | C116: GPL | D116: 87786 | E116: 18 | F116: 214 | G116: 2953.2 | H116: =IF(AND(OR('Панель BI'!$C$6="Все","февраль 2026"='Панель BI'!$C$6),OR('Панель BI'!$F$6="Все",$B116='Панель BI'!$F$6),OR('Панель BI'!$I$6="Все",$C116='Панель BI'!$I$6)),1,0) | I116: =IF(AND(OR('Панель BI'!$F$6="Все",$B116='Панель BI'!$F$6),OR('Панель BI'!$I$6="Все",$C116='Панель BI'!$I$6)),1,0)
A117: 2026-02 | B117: Комрат | C117: A92 | D117: 196324 | E117: 40 | F117: 676 | G117: 16359.2 | H117: =IF(AND(OR('Панель BI'!$C$6="Все","февраль 2026"='Панель BI'!$C$6),OR('Панель BI'!$F$6="Все",$B117='Панель BI'!$F$6),OR('Панель BI'!$I$6="Все",$C117='Панель BI'!$I$6)),1,0) | I117: =IF(AND(OR('Панель BI'!$F$6="Все",$B117='Панель BI'!$F$6),OR('Панель BI'!$I$6="Все",$C117='Панель BI'!$I$6)),1,0)
A118: 2026-02 | B118: Комрат | C118: A95 | D118: 205201 | E118: 41 | F118: 799 | G118: 20054.9 | H118: =IF(AND(OR('Панель BI'!$C$6="Все","февраль 2026"='Панель BI'!$C$6),OR('Панель BI'!$F$6="Все",$B118='Панель BI'!$F$6),OR('Панель BI'!$I$6="Все",$C118='Панель BI'!$I$6)),1,0) | I118: =IF(AND(OR('Панель BI'!$F$6="Все",$B118='Панель BI'!$F$6),OR('Панель BI'!$I$6="Все",$C118='Панель BI'!$I$6)),1,0)
... A127: 2026-02 | B127: Унгень | C127: GPL | D127: 40860 | E127: 8 | F127: 140 | G127: 1932 | H127: =IF(AND(OR('Панель BI'!$C$6="Все","февраль 2026"='Панель BI'!$C$6),OR('Панель BI'!$F$6="Все",$B127='Панель BI'!$F$6),OR('Панель BI'!$I$6="Все",$C127='Панель BI'!$I$6)),1,0) | I127: =IF(AND(OR('Панель BI'!$F$6="Все",$B127='Панель BI'!$F$6),OR('Панель BI'!$I$6="Все",$C127='Панель BI'!$I$6)),1,0)
A128: 2026-03 | B128: Бэлць | C128: A92 | D128: 222283 | E128: 44 | F128: 717 | G128: 17351.4 | H128: =IF(AND(OR('Панель BI'!$C$6="Все","март 2026"='Панель BI'!$C$6),OR('Панель BI'!$F$6="Все",$B128='Панель BI'!$F$6),OR('Панель BI'!$I$6="Все",$C128='Панель BI'!$I$6)),1,0) | I128: =IF(AND(OR('Панель BI'!$F$6="Все",$B128='Панель BI'!$F$6),OR('Панель BI'!$I$6="Все",$C128='Панель BI'!$I$6)),1,0)
A129: 2026-03 | B129: Бэлць | C129: A95 | D129: 184513 | E129: 38 | F129: 487 | G129: 12223.7 | H129: =IF(AND(OR('Панель BI'!$C$6="Все","март 2026"='Панель BI'!$C$6),OR('Панель BI'!$F$6="Все",$B129='Панель BI'!$F$6),OR('Панель BI'!$I$6="Все",$C129='Панель BI'!$I$6)),1,0) | I129: =IF(AND(OR('Панель BI'!$F$6="Все",$B129='Панель BI'!$F$6),OR('Панель BI'!$I$6="Все",$C129='Панель BI'!$I$6)),1,0)
A130: 2026-03 | B130: Бэлць | C130: DIESEL | D130: 238934 | E130: 42 | F130: 1016 | G130: 23774.4 | H130: =IF(AND(OR('Панель BI'!$C$6="Все","март 2026"='Панель BI'!$C$6),OR('Панель BI'!$F$6="Все",$B130='Панель BI'!$F$6),OR('Панель BI'!$I$6="Все",$C130='Панель BI'!$I$6)),1,0) | I130: =IF(AND(OR('Панель BI'!$F$6="Все",$B130='Панель BI'!$F$6),OR('Панель BI'!$I$6="Все",$C130='Панель BI'!$I$6)),1,0)
A131: 2026-03 | B131: Кагул | C131: A92 | D131: 146280 | E131: 31 | F131: 720 | G131: 17424 | H131: =IF(AND(OR('Панель BI'!$C$6="Все","март 2026"='Панель BI'!$C$6),OR('Панель BI'!$F$6="Все",$B131='Панель BI'!$F$6),OR('Панель BI'!$I$6="Все",$C131='Панель BI'!$I$6)),1,0) | I131: =IF(AND(OR('Панель BI'!$F$6="Все",$B131='Панель BI'!$F$6),OR('Панель BI'!$I$6="Все",$C131='Панель BI'!$I$6)),1,0)
A132: 2026-03 | B132: Кагул | C132: A95 | D132: 204438 | E132: 43 | F132: 562 | G132: 14106.2 | H132: =IF(AND(OR('Панель BI'!$C$6="Все","март 2026"='Панель BI'!$C$6),OR('Панель BI'!$F$6="Все",$B132='Панель BI'!$F$6),OR('Панель BI'!$I$6="Все",$C132='Панель BI'!$I$6)),1,0) | I132: =IF(AND(OR('Панель BI'!$F$6="Все",$B132='Панель BI'!$F$6),OR('Панель BI'!$I$6="Все",$C132='Панель BI'!$I$6)),1,0)
A133: 2026-03 | B133: Кагул | C133: DIESEL | D133: 218497 | E133: 44 | F133: 1503 | G133: 35170.2 | H133: =IF(AND(OR('Панель BI'!$C$6="Все","март 2026"='Панель BI'!$C$6),OR('Панель BI'!$F$6="Все",$B133='Панель BI'!$F$6),OR('Панель BI'!$I$6="Все",$C133='Панель BI'!$I$6)),1,0) | I133: =IF(AND(OR('Панель BI'!$F$6="Все",$B133='Панель BI'!$F$6),OR('Панель BI'!$I$6="Все",$C133='Панель BI'!$I$6)),1,0)
A134: 2026-03 | B134: Кишинёв | C134: A92 | D134: 266706 | E134: 53 | F134: 1294 | G134: 31314.8 | H134: =IF(AND(OR('Панель BI'!$C$6="Все","март 2026"='Панель BI'!$C$6),OR('Панель BI'!$F$6="Все",$B134='Панель BI'!$F$6),OR('Панель BI'!$I$6="Все",$C134='Панель BI'!$I$6)),1,0) | I134: =IF(AND(OR('Панель BI'!$F$6="Все",$B134='Панель BI'!$F$6),OR('Панель BI'!$I$6="Все",$C134='Панель BI'!$I$6)),1,0)
A135: 2026-03 | B135: Кишинёв | C135: A95 | D135: 199414 | E135: 40 | F135: 586 | G135: 14708.6 | H135: =IF(AND(OR('Панель BI'!$C$6="Все","март 2026"='Панель BI'!$C$6),OR('Панель BI'!$F$6="Все",$B135='Панель BI'!$F$6),OR('Панель BI'!$I$6="Все",$C135='Панель BI'!$I$6)),1,0) | I135: =IF(AND(OR('Панель BI'!$F$6="Все",$B135='Панель BI'!$F$6),OR('Панель BI'!$I$6="Все",$C135='Панель BI'!$I$6)),1,0)
A136: 2026-03 | B136: Кишинёв | C136: DIESEL | D136: 266151 | E136: 52 | F136: 849 | G136: 19866.6 | H136: =IF(AND(OR('Панель BI'!$C$6="Все","март 2026"='Панель BI'!$C$6),OR('Панель BI'!$F$6="Все",$B136='Панель BI'!$F$6),OR('Панель BI'!$I$6="Все",$C136='Панель BI'!$I$6)),1,0) | I136: =IF(AND(OR('Панель BI'!$F$6="Все",$B136='Панель BI'!$F$6),OR('Панель BI'!$I$6="Все",$C136='Панель BI'!$I$6)),1,0)
A137: 2026-03 | B137: Кишинёв | C137: GPL | D137: 44550 | E137: 9 | F137: 450 | G137: 6210 | H137: =IF(AND(OR('Панель BI'!$C$6="Все","март 2026"='Панель BI'!$C$6),OR('Панель BI'!$F$6="Все",$B137='Панель BI'!$F$6),OR('Панель BI'!$I$6="Все",$C137='Панель BI'!$I$6)),1,0) | I137: =IF(AND(OR('Панель BI'!$F$6="Все",$B137='Панель BI'!$F$6),OR('Панель BI'!$I$6="Все",$C137='Панель BI'!$I$6)),1,0)
A138: 2026-03 | B138: Комрат | C138: A92 | D138: 202056 | E138: 42 | F138: 944 | G138: 22844.8 | H138: =IF(AND(OR('Панель BI'!$C$6="Все","март 2026"='Панель BI'!$C$6),OR('Панель BI'!$F$6="Все",$B138='Панель BI'!$F$6),OR('Панель BI'!$I$6="Все",$C138='Панель BI'!$I$6)),1,0) | I138: =IF(AND(OR('Панель BI'!$F$6="Все",$B138='Панель BI'!$F$6),OR('Панель BI'!$I$6="Все",$C138='Панель BI'!$I$6)),1,0)
A139: 2026-03 | B139: Комрат | C139: A95 | D139: 284979 | E139: 55 | F139: 1021 | G139: 25627.1 | H139: =IF(AND(OR('Панель BI'!$C$6="Все","март 2026"='Панель BI'!$C$6),OR('Панель BI'!$F$6="Все",$B139='Панель BI'!$F$6),OR('Панель BI'!$I$6="Все",$C139='Панель BI'!$I$6)),1,0) | I139: =IF(AND(OR('Панель BI'!$F$6="Все",$B139='Панель BI'!$F$6),OR('Панель BI'!$I$6="Все",$C139='Панель BI'!$I$6)),1,0)
... A148: 2026-03 | B148: Унгень | C148: GPL | D148: 30894 | E148: 7 | F148: 106 | G148: 1462.8 | H148: =IF(AND(OR('Панель BI'!$C$6="Все","март 2026"='Панель BI'!$C$6),OR('Панель BI'!$F$6="Все",$B148='Панель BI'!$F$6),OR('Панель BI'!$I$6="Все",$C148='Панель BI'!$I$6)),1,0) | I148: =IF(AND(OR('Панель BI'!$F$6="Все",$B148='Панель BI'!$F$6),OR('Панель BI'!$I$6="Все",$C148='Панель BI'!$I$6)),1,0)
A149: 2026-04 | B149: Бэлць | C149: A92 | D149: 206322 | E149: 40 | F149: 678 | G149: 16407.6 | H149: =IF(AND(OR('Панель BI'!$C$6="Все","апрель 2026"='Панель BI'!$C$6),OR('Панель BI'!$F$6="Все",$B149='Панель BI'!$F$6),OR('Панель BI'!$I$6="Все",$C149='Панель BI'!$I$6)),1,0) | I149: =IF(AND(OR('Панель BI'!$F$6="Все",$B149='Панель BI'!$F$6),OR('Панель BI'!$I$6="Все",$C149='Панель BI'!$I$6)),1,0)
A150: 2026-04 | B150: Бэлць | C150: A95 | D150: 246933 | E150: 48 | F150: 1067 | G150: 26781.7 | H150: =IF(AND(OR('Панель BI'!$C$6="Все","апрель 2026"='Панель BI'!$C$6),OR('Панель BI'!$F$6="Все",$B150='Панель BI'!$F$6),OR('Панель BI'!$I$6="Все",$C150='Панель BI'!$I$6)),1,0) | I150: =IF(AND(OR('Панель BI'!$F$6="Все",$B150='Панель BI'!$F$6),OR('Панель BI'!$I$6="Все",$C150='Панель BI'!$I$6)),1,0)
A151: 2026-04 | B151: Бэлць | C151: DIESEL | D151: 259237 | E151: 53 | F151: 763 | G151: 17854.2 | H151: =IF(AND(OR('Панель BI'!$C$6="Все","апрель 2026"='Панель BI'!$C$6),OR('Панель BI'!$F$6="Все",$B151='Панель BI'!$F$6),OR('Панель BI'!$I$6="Все",$C151='Панель BI'!$I$6)),1,0) | I151: =IF(AND(OR('Панель BI'!$F$6="Все",$B151='Панель BI'!$F$6),OR('Панель BI'!$I$6="Все",$C151='Панель BI'!$I$6)),1,0)
A152: 2026-04 | B152: Кагул | C152: A92 | D152: 159204 | E152: 35 | F152: 796 | G152: 19263.2 | H152: =IF(AND(OR('Панель BI'!$C$6="Все","апрель 2026"='Панель BI'!$C$6),OR('Панель BI'!$F$6="Все",$B152='Панель BI'!$F$6),OR('Панель BI'!$I$6="Все",$C152='Панель BI'!$I$6)),1,0) | I152: =IF(AND(OR('Панель BI'!$F$6="Все",$B152='Панель BI'!$F$6),OR('Панель BI'!$I$6="Все",$C152='Панель BI'!$I$6)),1,0)
A153: 2026-04 | B153: Кагул | C153: A95 | D153: 175327 | E153: 35 | F153: 673 | G153: 16892.3 | H153: =IF(AND(OR('Панель BI'!$C$6="Все","апрель 2026"='Панель BI'!$C$6),OR('Панель BI'!$F$6="Все",$B153='Панель BI'!$F$6),OR('Панель BI'!$I$6="Все",$C153='Панель BI'!$I$6)),1,0) | I153: =IF(AND(OR('Панель BI'!$F$6="Все",$B153='Панель BI'!$F$6),OR('Панель BI'!$I$6="Все",$C153='Панель BI'!$I$6)),1,0)
A154: 2026-04 | B154: Кагул | C154: DIESEL | D154: 206330 | E154: 41 | F154: 670 | G154: 15678 | H154: =IF(AND(OR('Панель BI'!$C$6="Все","апрель 2026"='Панель BI'!$C$6),OR('Панель BI'!$F$6="Все",$B154='Панель BI'!$F$6),OR('Панель BI'!$I$6="Все",$C154='Панель BI'!$I$6)),1,0) | I154: =IF(AND(OR('Панель BI'!$F$6="Все",$B154='Панель BI'!$F$6),OR('Панель BI'!$I$6="Все",$C154='Панель BI'!$I$6)),1,0)
A155: 2026-04 | B155: Кишинёв | C155: A92 | D155: 226874 | E155: 44 | F155: 1126 | G155: 27249.2 | H155: =IF(AND(OR('Панель BI'!$C$6="Все","апрель 2026"='Панель BI'!$C$6),OR('Панель BI'!$F$6="Все",$B155='Панель BI'!$F$6),OR('Панель BI'!$I$6="Все",$C155='Панель BI'!$I$6)),1,0) | I155: =IF(AND(OR('Панель BI'!$F$6="Все",$B155='Панель BI'!$F$6),OR('Панель BI'!$I$6="Все",$C155='Панель BI'!$I$6)),1,0)
A156: 2026-04 | B156: Кишинёв | C156: A95 | D156: 283863 | E156: 57 | F156: 1137 | G156: 28538.7 | H156: =IF(AND(OR('Панель BI'!$C$6="Все","апрель 2026"='Панель BI'!$C$6),OR('Панель BI'!$F$6="Все",$B156='Панель BI'!$F$6),OR('Панель BI'!$I$6="Все",$C156='Панель BI'!$I$6)),1,0) | I156: =IF(AND(OR('Панель BI'!$F$6="Все",$B156='Панель BI'!$F$6),OR('Панель BI'!$I$6="Все",$C156='Панель BI'!$I$6)),1,0)
...

Sheet КубРейсы
A1: Месяц | B1: Тип рейса | C1: Рейсов | D1: Норматив, км | E1: Факт, км | F1: Лишний пробег, км | G1: Начислено, лей | H1: Норма ДТ, л | I1: Факт ДТ, л | J1: В срезе | K1: В срезе без месяца
A2: 2025-09 | B2: DOMESTIC | C2: 228 | D2: 70839 | E2: 72336 | F2: 1621 | G2: 329754.01 | H2: 23465 | I2: 23540 | J2: =IF(AND(OR('Панель BI'!$C$6="Все","сентябрь 2025"='Панель BI'!$C$6),OR('Панель BI'!$L$6="Все",$B2='Панель BI'!$L$6)),1,0) | K2: =IF(OR('Панель BI'!$L$6="Все",$B2='Панель BI'!$L$6),1,0)
A3: 2025-09 | B3: IMPORT | C3: 38 | D3: 32960 | E3: 33711 | F3: 811 | G3: 90639.99 | H3: 10836 | I3: 10949 | J3: =IF(AND(OR('Панель BI'!$C$6="Все","сентябрь 2025"='Панель BI'!$C$6),OR('Панель BI'!$L$6="Все",$B3='Панель BI'!$L$6)),1,0) | K3: =IF(OR('Панель BI'!$L$6="Все",$B3='Панель BI'!$L$6),1,0)
A4: 2025-10 | B4: DOMESTIC | C4: 212 | D4: 63274 | E4: 64319 | F4: 1181 | G4: 300392.69 | H4: 20893 | I4: 21032 | J4: =IF(AND(OR('Панель BI'!$C$6="Все","октябрь 2025"='Панель BI'!$C$6),OR('Панель BI'!$L$6="Все",$B4='Панель BI'!$L$6)),1,0) | K4: =IF(OR('Панель BI'!$L$6="Все",$B4='Панель BI'!$L$6),1,0)
A5: 2025-10 | B5: IMPORT | C5: 54 | D5: 49866 | E5: 51344 | F5: 1531 | G5: 134005.06 | H5: 16431 | I5: 16515 | J5: =IF(AND(OR('Панель BI'!$C$6="Все","октябрь 2025"='Панель BI'!$C$6),OR('Панель BI'!$L$6="Все",$B5='Панель BI'!$L$6)),1,0) | K5: =IF(OR('Панель BI'!$L$6="Все",$B5='Панель BI'!$L$6),1,0)
A6: 2025-11 | B6: DOMESTIC | C6: 204 | D6: 62403 | E6: 63523 | F6: 1210 | G6: 294096.78 | H6: 20663 | I6: 20788 | J6: =IF(AND(OR('Панель BI'!$C$6="Все","ноябрь 2025"='Панель BI'!$C$6),OR('Панель BI'!$L$6="Все",$B6='Панель BI'!$L$6)),1,0) | K6: =IF(OR('Панель BI'!$L$6="Все",$B6='Панель BI'!$L$6),1,0)
A7: 2025-11 | B7: IMPORT | C7: 52 | D7: 44933 | E7: 45719 | F7: 873 | G7: 121101.2 | H7: 14823 | I7: 14872 | J7: =IF(AND(OR('Панель BI'!$C$6="Все","ноябрь 2025"='Панель BI'!$C$6),OR('Панель BI'!$L$6="Все",$B7='Панель BI'!$L$6)),1,0) | K7: =IF(OR('Панель BI'!$L$6="Все",$B7='Панель BI'!$L$6),1,0)
A8: 2025-12 | B8: DOMESTIC | C8: 237 | D8: 70460 | E8: 71694 | F8: 1382 | G8: 334621.18 | H8: 23273 | I8: 23499 | J8: =IF(AND(OR('Панель BI'!$C$6="Все","декабрь 2025"='Панель BI'!$C$6),OR('Панель BI'!$L$6="Все",$B8='Панель BI'!$L$6)),1,0) | K8: =IF(OR('Панель BI'!$L$6="Все",$B8='Панель BI'!$L$6),1,0)
A9: 2025-12 | B9: IMPORT | C9: 59 | D9: 50577 | E9: 51615 | F9: 1146 | G9: 139333.04 | H9: 16819 | I9: 16887 | J9: =IF(AND(OR('Панель BI'!$C$6="Все","декабрь 2025"='Панель BI'!$C$6),OR('Панель BI'!$L$6="Все",$B9='Панель BI'!$L$6)),1,0) | K9: =IF(OR('Панель BI'!$L$6="Все",$B9='Панель BI'!$L$6),1,0)
A10: 2026-01 | B10: DOMESTIC | C10: 226 | D10: 67736 | E10: 69099 | F10: 1465 | G10: 320536.16 | H10: 22300 | I10: 22387 | J10: =IF(AND(OR('Панель BI'!$C$6="Все","январь 2026"='Панель BI'!$C$6),OR('Панель BI'!$L$6="Все",$B10='Панель BI'!$L$6)),1,0) | K10: =IF(OR('Панель BI'!$L$6="Все",$B10='Панель BI'!$L$6),1,0)
A11: 2026-01 | B11: IMPORT | C11: 57 | D11: 49074 | E11: 49823 | F11: 818 | G11: 134954.89 | H11: 16397 | I11: 16468 | J11: =IF(AND(OR('Панель BI'!$C$6="Все","январь 2026"='Панель BI'!$C$6),OR('Панель BI'!$L$6="Все",$B11='Панель BI'!$L$6)),1,0) | K11: =IF(OR('Панель BI'!$L$6="Все",$B11='Панель BI'!$L$6),1,0)
A12: 2026-02 | B12: DOMESTIC | C12: 198 | D12: 58947 | E12: 60316 | F12: 1446 | G12: 279285.08 | H12: 19433 | I12: 19448 | J12: =IF(AND(OR('Панель BI'!$C$6="Все","февраль 2026"='Панель BI'!$C$6),OR('Панель BI'!$L$6="Все",$B12='Панель BI'!$L$6)),1,0) | K12: =IF(OR('Панель BI'!$L$6="Все",$B12='Панель BI'!$L$6),1,0)
A13: 2026-02 | B13: IMPORT | C13: 51 | D13: 44302 | E13: 45258 | F13: 1034 | G13: 121829.7 | H13: 14742 | I13: 14848 | J13: =IF(AND(OR('Панель BI'!$C$6="Все","февраль 2026"='Панель BI'!$C$6),OR('Панель BI'!$L$6="Все",$B13='Панель BI'!$L$6)),1,0) | K13: =IF(OR('Панель BI'!$L$6="Все",$B13='Панель BI'!$L$6),1,0)
A14: 2026-03 | B14: DOMESTIC | C14: 233 | D14: 72373 | E14: 73854 | F14: 1633 | G14: 337511.27 | H14: 23942 | I14: 24042 | J14: =IF(AND(OR('Панель BI'!$C$6="Все","март 2026"='Панель BI'!$C$6),OR('Панель BI'!$L$6="Все",$B14='Панель BI'!$L$6)),1,0) | K14: =IF(OR('Панель BI'!$L$6="Все",$B14='Панель BI'!$L$6),1,0)
A15: 2026-03 | B15: IMPORT | C15: 49 | D15: 44574 | E15: 45470 | F15: 978 | G15: 122578.54 | H15: 14722 | I15: 14777 | J15: =IF(AND(OR('Панель BI'!$C$6="Все","март 2026"='Панель BI'!$C$6),OR('Панель BI'!$L$6="Все",$B15='Панель BI'!$L$6)),1,0) | K15: =IF(OR('Панель BI'!$L$6="Все",$B15='Панель BI'!$L$6),1,0)
A16: 2026-04 | B16: DOMESTIC | C16: 236 | D16: 70982 | E16: 72580 | F16: 1731 | G16: 334270.54 | H16: 23499 | I16: 23610 | J16: =IF(AND(OR('Панель BI'!$C$6="Все","апрель 2026"='Панель BI'!$C$6),OR('Панель BI'!$L$6="Все",$B16='Панель BI'!$L$6)),1,0) | K16: =IF(OR('Панель BI'!$L$6="Все",$B16='Панель BI'!$L$6),1,0)
A17: 2026-04 | B17: IMPORT | C17: 41 | D17: 36660 | E17: 37444 | F17: 816 | G17: 95475.35 | H17: 12172 | I17: 12307 | J17: =IF(AND(OR('Панель BI'!$C$6="Все","апрель 2026"='Панель BI'!$C$6),OR('Панель BI'!$L$6="Все",$B17='Панель BI'!$L$6)),1,0) | K17: =IF(OR('Панель BI'!$L$6="Все",$B17='Панель BI'!$L$6),1,0)
A18: 2026-05 | B18: DOMESTIC | C18: 209 | D18: 62272 | E18: 63377 | F18: 1208 | G18: 291568.73 | H18: 20530 | I18: 20668 | J18: =IF(AND(OR('Панель BI'!$C$6="Все","май 2026"='Панель BI'!$C$6),OR('Панель BI'!$L$6="Все",$B18='Панель BI'!$L$6)),1,0) | K18: =IF(OR('Панель BI'!$L$6="Все",$B18='Панель BI'!$L$6),1,0)
A19: 2026-05 | B19: IMPORT | C19: 57 | D19: 50133 | E19: 51350 | F19: 1273 | G19: 137866.31 | H19: 16541 | I19: 16538 | J19: =IF(AND(OR('Панель BI'!$C$6="Все","май 2026"='Панель BI'!$C$6),OR('Панель BI'!$L$6="Все",$B19='Панель BI'!$L$6)),1,0) | K19: =IF(OR('Панель BI'!$L$6="Все",$B19='Панель BI'!$L$6),1,0)
A20: 2026-06 | B20: DOMESTIC | C20: 227 | D20: 68082 | E20: 69566 | F20: 1577 | G20: 322970.91 | H20: 22570 | I20: 22715 | J20: =IF(AND(OR('Панель BI'!$C$6="Все","июнь 2026"='Панель BI'!$C$6),OR('Панель BI'!$L$6="Все",$B20='Панель BI'!$L$6)),1,0) | K20: =IF(OR('Панель BI'!$L$6="Все",$B20='Панель BI'!$L$6),1,0)
A21: 2026-06 | B21: IMPORT | C21: 39 | D21: 35958 | E21: 36619 | F21: 737 | G21: 98884.51 | H21: 11748 | I21: 11927 | J21: =IF(AND(OR('Панель BI'!$C$6="Все","июнь 2026"='Панель BI'!$C$6),OR('Панель BI'!$L$6="Все",$B21='Панель BI'!$L$6)),1,0) | K21: =IF(OR('Панель BI'!$L$6="Все",$B21='Панель BI'!$L$6),1,0)
A22: 2026-07 | B22: DOMESTIC | C22: 239 | D22: 71628 | E22: 73130 | F22: 1634 | G22: 340377.47 | H22: 23663 | I22: 23729 | J22: =IF(AND(OR('Панель BI'!$C$6="Все","июль 2026"='Панель BI'!$C$6),OR('Панель BI'!$L$6="Все",$B22='Панель BI'!$L$6)),1,0) | K22: =IF(OR('Панель BI'!$L$6="Все",$B22='Панель BI'!$L$6),1,0)
A23: 2026-07 | B23: IMPORT | C23: 48 | D23: 41721 | E23: 42647 | F23: 1029 | G23: 114732.75 | H23: 13820 | I23: 13865 | J23: =IF(AND(OR('Панель BI'!$C$6="Все","июль 2026"='Панель BI'!$C$6),OR('Панель BI'!$L$6="Все",$B23='Панель BI'!$L$6)),1,0) | K23: =IF(OR('Панель BI'!$L$6="Все",$B23='Панель BI'!$L$6),1,0)
A24: 2026-08 | B24: DOMESTIC | C24: 232 | D24: 69275 | E24: 70446 | F24: 1310 | G24: 329957.05 | H24: 22919 | I24: 23082 | J24: =IF(AND(OR('Панель BI'!$C$6="Все","август 2026"='Панель BI'!$C$6),OR('Панель BI'!$L$6="Все",$B24='Панель BI'!$L$6)),1,0) | K24: =IF(OR('Панель BI'!$L$6="Все",$B24='Панель BI'!$L$6),1,0)
A25: 2026-08 | B25: IMPORT | C25: 42 | D25: 35666 | E25: 36542 | F25: 907 | G25: 98081.2 | H25: 11883 | I25: 12094 | J25: =IF(AND(OR('Панель BI'!$C$6="Все","август 2026"='Панель BI'!$C$6),OR('Панель BI'!$L$6="Все",$B25='Панель BI'!$L$6)),1,0) | K25: =IF(OR('Панель BI'!$L$6="Все",$B25='Панель BI'!$L$6),1,0)
A26: 2026-09 | B26: DOMESTIC | C26: 223 | D26: 69304 | E26: 71028 | F26: 1845 | G26: 242747.63 | H26: 22842 | I26: 22968 | J26: =IF(AND(OR('Панель BI'!$C$6="Все","сентябрь 2026"='Панель BI'!$C$6),OR('Панель BI'!$L$6="Все",$B26='Панель BI'!$L$6)),1,0) | K26: =IF(OR('Панель BI'!$L$6="Все",$B26='Панель BI'!$L$6),1,0)
A27: 2026-09 | B27: IMPORT | C27: 43 | D27: 38057 | E27: 38720 | F27: 713 | G27: 130827.9 | H27: 12659 | I27: 12825 | J27: =IF(AND(OR('Панель BI'!$C$6="Все","сентябрь 2026"='Панель BI'!$C$6),OR('Панель BI'!$L$6="Все",$B27='Панель BI'!$L$6)),1,0) | K27: =IF(OR('Панель BI'!$L$6="Все",$B27='Панель BI'!$L$6),1,0)

Sheet Самопроверка
A2: Самопроверка методики
A3: Лист существует только для сгенерированного набора: в него намеренно заложено известное число дефектов каждого вида.
A5: Зачем это нужно
A6: • Проверка, которой нечего находить, ничего не доказывает: она одинаково молчит и когда всё чисто, и когда сама сломана.
A7: • Поэтому набор данных генерируется с известным числом нарушений каждого вида, а проверка прогоняется вслепую. Совпадение «подложено» и «найдено» по всем процедурам — доказательство, что методика ловит то, что должна, и не выдумывает лишнего.
A8: • Расхождение в любую сторону — отказ: «найдено меньше» означает пропуск, «найдено больше» — ложные срабатывания, и то и другое делает вывод непригодным.
A10: Код | B10: Процедура | C10: Подложено дефектов | D10: Найдено | E10: Разница | F10: Итог
A11: T-01 | B11: Пересчёт заработной платы водителей | C11: 18 | D11: 18 | E11: 0 | F11: Совпало
A12: T-02 | B12: Целостность периодов действия ставки | C12: 0 | D12: 0 | E12: 0 | F12: Совпало
A13: T-03 | B13: Слив отсеками целиком | C13: 10 | D13: 10 | E13: 0 | F13: Совпало
A14: T-04 | B14: Контроль переполнения резервуара | C14: 5 | D14: 5 | E14: 0 | F14: Совпало
A15: T-05 | B15: Сверка отгрузки и приёмки | C15: 197 | D15: 197 | E15: 0 | F15: Совпало
A16: T-06 | B16: Необоснованный пробег | C16: 151 | D16: 151 | E16: 0 | F16: Совпало
A17: T-07 | B17: Перерасход топлива бензовозом | C17: 96 | D17: 96 | E17: 0 | F17: Совпало
A18: T-08 | B18: Полнота учёта рейса | C18: 19 | D18: 19 | E18: 0 | F18: Совпало
A19: T-09 | B19: Хронология исполнения рейса | C19: 35 | D19: 35 | E19: 0 | F19: Совпало
A20: T-10 | B20: Разделение полномочий | C20: 74 | D20: 74 | E20: 0 | F20: Совпало
A21: T-11 | B21: Дублирование документов | C21: 3 | D21: 3 | E21: 0 | F21: Совпало
A22: T-12 | B22: Непротиворечивость справочников | C22: 2 | D22: 2 | E22: 0 | F22: Совпало
A23: T-13 | B23: Покрытие страхового запаса | C23: 6 | D23: 6 | E23: 0 | F23: Совпало
A25: ИТОГ: методика воспроизвела все заложенные дефекты и не дала ложных срабатываний.

Sheet Методика
A2: Методика, шкалы и определения
A4: Подход
A5: 1. Тестирование полной популяции (data & analytics): каждый документ периода пересчитан независимо, выборочный метод применён только там, где контроль не отражён в данных.
A6: 2. Пересчёт выполнен отдельной реализацией формул (modules/autopark/audit.py), не использующей проверяемый код расчёта, — совпадение результата не может быть следствием общей ошибки.
A7: 3. Оценка контроля даётся по двум измерениям: дизайн (предотвращает ли правило ошибку в принципе) и операционная эффективность (срабатывало ли оно на данных периода).
A8: 4. Контроль с дефектом дизайна не получает оценку выше «требует улучшения», даже если отклонений в периоде не обнаружено.
A9: 5. Значимость находки определяется долей отклонений и денежной оценкой, а не экспертным суждением.
A11: Предмет проверки
A12: 1. Расчёт заработной платы водителей бензовозов по нормативному пробегу (ТЗ «Автоматизация расчёта расходов автопарка» от 18.09.2026).
A13: 2. Планирование потребности АЗС в топливе, формирование и исполнение рейсов (ТЗ «Автоматизация распределения топлива» от 18.09.2026).
A14: 3. Контроль фактического пробега и расхода дизельного топлива бензовозами.
A15: 4. Настройки контура, действующие по периодам: ставка за километр, лимиты резервуаров, состав отсеков и групп АЗС.
... A39: • Цены продуктов — последнее решение ANRE на дату окончания периода.
